{"code": "6239", "market": "twse", "rows": [{"date": "2025-04-14", "taiex": 19513.09, "high": 115.5, "low": 111.0, "close": 113.5, "lots": 5759, "change_pct": null, "ma5": null, "ma10": null, "ma20": null, "ma60": null, "rsi6": null, "rsi12": null, "kd_k": null, "kd_d": null, "macd_osc": null}, {"date": "2025-04-15", "taiex": 19857.67, "high": 116.5, "low": 113.5, "close": 115.0, "lots": 3057, "change_pct": 1.3215859030837005, "ma5": null, "ma10": null, "ma20": null, "ma60": null, "rsi6": null, "rsi12": null, "kd_k": null, "kd_d": null, "macd_osc": null}, {"date": "2025-04-16", "taiex": 19468.0, "high": 114.0, "low": 111.0, "close": 111.0, "lots": 4097, "change_pct": -3.4782608695652173, "ma5": null, "ma10": null, "ma20": null, "ma60": null, "rsi6": null, "rsi12": null, "kd_k": null, "kd_d": null, "macd_osc": null}, {"date": "2025-04-17", "taiex": 19338.73, "high": 113.5, "low": 109.5, "close": 111.5, "lots": 3086, "change_pct": 0.45045045045045046, "ma5": null, "ma10": null, "ma20": null, "ma60": null, "rsi6": null, "rsi12": null, "kd_k": null, "kd_d": null, "macd_osc": null}, {"date": "2025-04-18", "taiex": 19395.03, "high": 113.0, "low": 108.5, "close": 110.5, "lots": 6994, "change_pct": -0.8968609865470852, "ma5": 112.3, "ma10": null, "ma20": null, "ma60": null, "rsi6": null, "rsi12": null, "kd_k": null, "kd_d": null, "macd_osc": null}, {"date": "2025-04-21", "taiex": 19106.2, "high": 113.5, "low": 109.5, "close": 110.0, "lots": 6930, "change_pct": -0.4524886877828055, "ma5": 111.6, "ma10": null, "ma20": null, "ma60": null, "rsi6": null, "rsi12": null, "kd_k": null, "kd_d": null, "macd_osc": null}, {"date": "2025-04-22", "taiex": 18793.43, "high": 112.5, "low": 109.0, "close": 109.5, "lots": 6906, "change_pct": -0.45454545454545453, "ma5": 110.5, "ma10": null, "ma20": null, "ma60": null, "rsi6": 25.0, "rsi12": null, "kd_k": null, "kd_d": null, "macd_osc": null}, {"date": "2025-04-23", "taiex": 19639.14, "high": 116.5, "low": 111.0, "close": 116.5, "lots": 9173, "change_pct": 6.392694063926941, "ma5": 111.6, "ma10": null, "ma20": null, "ma60": null, "rsi6": 63.41463414634146, "rsi12": null, "kd_k": null, "kd_d": null, "macd_osc": null}, {"date": "2025-04-24", "taiex": 19478.81, "high": 117.5, "low": 112.0, "close": 114.0, "lots": 7841, "change_pct": -2.1459227467811157, "ma5": 112.1, "ma10": null, "ma20": null, "ma60": null, "rsi6": 51.99999999999999, "rsi12": null, "kd_k": 53.703703703703695, "kd_d": 51.234567901234556, "macd_osc": null}, {"date": "2025-04-25", "taiex": 19872.73, "high": 116.0, "low": 111.0, "close": 111.5, "lots": 6867, "change_pct": -2.1929824561403506, "ma5": 112.3, "ma10": 112.3, "ma20": null, "ma60": null, "rsi6": 42.76315789473684, "rsi12": null, "kd_k": 46.91358024691357, "kd_d": 49.79423868312755, "macd_osc": null}, {"date": "2025-04-28", "taiex": 20034.41, "high": 112.5, "low": 111.0, "close": 111.5, "lots": 4559, "change_pct": 0.0, "ma5": 112.6, "ma10": 112.1, "ma20": null, "ma60": null, "rsi6": 42.76315789473684, "rsi12": null, "kd_k": 42.386831275720155, "kd_d": 47.32510288065842, "macd_osc": null}, {"date": "2025-04-29", "taiex": 20232.63, "high": 112.5, "low": 110.0, "close": 111.5, "lots": 5810, "change_pct": 0.0, "ma5": 113.0, "ma10": 111.75, "ma20": null, "ma60": null, "rsi6": 42.76315789473684, "rsi12": null, "kd_k": 39.36899862825788, "kd_d": 44.67306812985824, "macd_osc": null}, {"date": "2025-04-30", "taiex": 20235.03, "high": 111.0, "low": 107.0, "close": 108.5, "lots": 11220, "change_pct": -2.690582959641256, "ma5": 111.4, "ma10": 111.5, "ma20": null, "ma60": null, "rsi6": 31.251923195273562, "rsi12": 39.130434782608695, "kd_k": 31.007903847410013, "kd_d": 40.11801336904216, "macd_osc": null}, {"date": "2025-05-02", "taiex": 20787.64, "high": 111.0, "low": 108.5, "close": 109.0, "lots": 6066, "change_pct": 0.4608294930875576, "ma5": 110.4, "ma10": 111.25, "ma20": null, "ma60": null, "rsi6": 34.76404185986755, "rsi12": 40.54054054054053, "kd_k": 27.021142247479688, "kd_d": 35.752389661854664, "macd_osc": null}, {"date": "2025-05-05", "taiex": 20532.99, "high": 110.0, "low": 105.5, "close": 105.5, "lots": 5003, "change_pct": -3.211009174311927, "ma5": 109.2, "ma10": 110.75, "ma20": null, "ma60": null, "rsi6": 24.32533429878572, "rsi12": 34.44676409185804, "kd_k": 18.014094831653125, "kd_d": 29.839624718454147, "macd_osc": null}, {"date": "2025-05-06", "taiex": 20522.59, "high": 109.0, "low": 103.5, "close": 108.0, "lots": 3979, "change_pct": 2.3696682464454977, "ma5": 108.5, "ma10": 110.55, "ma20": null, "ma60": null, "rsi6": 39.81545094226062, "rsi12": 41.31980681018372, "kd_k": 22.72368226872113, "kd_d": 27.467643901876475, "macd_osc": null}, {"date": "2025-05-07", "taiex": 20546.49, "high": 108.5, "low": 107.0, "close": 107.5, "lots": 3175, "change_pct": -0.4629629629629629, "ma5": 107.7, "ma10": 110.35, "ma20": null, "ma60": null, "rsi6": 37.9510504048307, "rsi12": 40.395728223191924, "kd_k": 24.672931036290276, "kd_d": 26.536072946681074, "macd_osc": null}, {"date": "2025-05-08", "taiex": 20543.4, "high": 112.0, "low": 107.0, "close": 111.0, "lots": 4981, "change_pct": 3.255813953488372, "ma5": 108.2, "ma10": 109.8, "ma20": null, "ma60": null, "rsi6": 55.4674380403187, "rsi12": 49.09012158566343, "kd_k": 36.44862069086018, "kd_d": 29.84025552807411, "macd_osc": null}, {"date": "2025-05-09", "taiex": 20915.04, "high": 114.5, "low": 110.5, "close": 114.0, "lots": 5266, "change_pct": 2.7027027027027026, "ma5": 109.2, "ma10": 109.8, "ma20": null, "ma60": null, "rsi6": 65.48840448315323, "rsi12": 55.200608089870386, "kd_k": 56.11726227875527, "kd_d": 38.599257778301165, "macd_osc": null}, {"date": "2025-05-12", "taiex": 21129.54, "high": 116.0, "low": 114.0, "close": 114.5, "lots": 4952, "change_pct": 0.43859649122807015, "ma5": 111.0, "ma10": 110.1, "ma20": 111.2, "ma60": null, "rsi6": 66.97471154825965, "rsi12": 56.15737810892996, "kd_k": 66.74484151917018, "kd_d": 47.9811190252575, "macd_osc": null}, {"date": "2025-05-13", "taiex": 21330.14, "high": 119.0, "low": 114.5, "close": 115.0, "lots": 6240, "change_pct": 0.43668122270742354, "ma5": 112.4, "ma10": 110.45, "ma20": 111.275, "ma60": null, "rsi6": 68.59759616924539, "rsi12": 57.15557972935714, "kd_k": 69.22774380847903, "kd_d": 55.063327286331344, "macd_osc": null}, {"date": "2025-05-14", "taiex": 21782.87, "high": 120.5, "low": 115.5, "close": 120.0, "lots": 11916, "change_pct": 4.3478260869565215, "ma5": 114.9, "ma10": 111.3, "ma20": 111.525, "ma60": null, "rsi6": 80.24618394552525, "rsi12": 65.67988584251094, "kd_k": 78.50477038212327, "kd_d": 62.87714165159531, "macd_osc": null}, {"date": "2025-05-15", "taiex": 21730.25, "high": 120.0, "low": 118.5, "close": 119.5, "lots": 4372, "change_pct": -0.4166666666666667, "ma5": 116.6, "ma10": 112.4, "ma20": 111.95, "ma60": null, "rsi6": 76.82637404893678, "rsi12": 64.28460916448468, "kd_k": 83.70906260769002, "kd_d": 69.82111530362687, "macd_osc": null}, {"date": "2025-05-16", "taiex": 21843.69, "high": 120.0, "low": 117.5, "close": 118.5, "lots": 3898, "change_pct": -0.8368200836820083, "ma5": 117.5, "ma10": 113.35, "ma20": 112.3, "ma60": null, "rsi6": 69.69772223612318, "rsi12": 61.437024306525984, "kd_k": 85.21780644434236, "kd_d": 74.95334568386536, "macd_osc": null}, {"date": "2025-05-19", "taiex": 21523.83, "high": 119.5, "low": 116.0, "close": 116.0, "lots": 5255, "change_pct": -2.109704641350211, "ma5": 117.8, "ma10": 114.4, "ma20": 112.575, "ma60": null, "rsi6": 54.520886601712114, "rsi12": 54.81490633998149, "kd_k": 79.03409318511711, "kd_d": 76.31359485094927, "macd_osc": null}, {"date": "2025-05-20", "taiex": 21526.03, "high": 119.0, "low": 116.0, "close": 116.5, "lots": 5035, "change_pct": 0.43103448275862066, "ma5": 118.1, "ma10": 115.25, "ma20": 112.9, "ma60": null, "rsi6": 56.77960761656287, "rsi12": 55.853116670220786, "kd_k": 76.14618558020153, "kd_d": 76.25779176070003, "macd_osc": null}, {"date": "2025-05-21", "taiex": 21803.91, "high": 119.5, "low": 116.0, "close": 118.5, "lots": 4991, "change_pct": 1.7167381974248928, "ma5": 117.8, "ma10": 116.35, "ma20": 113.35, "ma60": null, "rsi6": 65.09958941909142, "rsi12": 59.87604626603359, "kd_k": 77.43079038680102, "kd_d": 76.64879130273368, "macd_osc": null}, {"date": "2025-05-22", "taiex": 21670.96, "high": 119.0, "low": 117.5, "close": 118.0, "lots": 3413, "change_pct": -0.42194092827004215, "ma5": 117.5, "ma10": 117.05, "ma20": 113.425, "ma60": null, "rsi6": 61.54532297924557, "rsi12": 58.42405941904694, "kd_k": 72.13334743735453, "kd_d": 75.1436433476073, "macd_osc": null}, {"date": "2025-05-23", "taiex": 21652.24, "high": 121.0, "low": 118.5, "close": 119.5, "lots": 5142, "change_pct": 1.2711864406779663, "ma5": 117.7, "ma10": 117.6, "ma20": 113.7, "ma60": null, "rsi6": 67.86205357078359, "rsi12": 61.481048187235, "kd_k": 73.72992393259533, "kd_d": 74.67240354260329, "macd_osc": null}, {"date": "2025-05-26", "taiex": 21536.57, "high": 120.0, "low": 116.5, "close": 118.5, "lots": 5690, "change_pct": -0.8368200836820083, "ma5": 118.2, "ma10": 118.0, "ma20": 114.05, "ma60": null, "rsi6": 59.97999594604799, "rsi12": 58.360246450547315, "kd_k": 67.33510080354839, "kd_d": 72.22663596291832, "macd_osc": null}, {"date": "2025-05-27", "taiex": 21336.54, "high": 119.5, "low": 116.0, "close": 116.5, "lots": 4337, "change_pct": -1.6877637130801686, "ma5": 118.2, "ma10": 118.15, "ma20": 114.3, "ma60": null, "rsi6": 46.90496640196914, "rsi12": 52.54130089387089, "kd_k": 48.22340053569892, "kd_d": 64.22555748717852, "macd_osc": null}, {"date": "2025-05-28", "taiex": 21357.72, "high": 118.5, "low": 115.5, "close": 117.0, "lots": 2783, "change_pct": 0.4291845493562232, "ma5": 117.9, "ma10": 117.85, "ma20": 114.575, "ma60": null, "rsi6": 50.16408340376804, "rsi12": 53.797676689599626, "kd_k": 41.23984278137503, "kd_d": 56.56365258524402, "macd_osc": null}, {"date": "2025-05-29", "taiex": 21347.3, "high": 118.5, "low": 117.0, "close": 117.0, "lots": 2907, "change_pct": 0.0, "ma5": 117.7, "ma10": 117.6, "ma20": 115.0, "ma60": null, "rsi6": 50.16408340376804, "rsi12": 53.797676689599626, "kd_k": 36.58413761182578, "kd_d": 49.90381426077127, "macd_osc": null}, {"date": "2025-06-02", "taiex": 21002.71, "high": 116.0, "low": 113.0, "close": 113.5, "lots": 4509, "change_pct": -2.9914529914529915, "ma5": 116.5, "ma10": 117.1, "ma20": 115.225, "ma60": null, "rsi6": 30.989630479032442, "rsi12": 44.077102287884195, "kd_k": 26.472758407883852, "kd_d": 42.0934623098088, "macd_osc": -0.6935321283836071}, {"date": "2025-06-03", "taiex": 21126.93, "high": 116.0, "low": 114.0, "close": 116.0, "lots": 3224, "change_pct": 2.2026431718061676, "ma5": 116.0, "ma10": 117.1, "ma20": 115.75, "ma60": null, "rsi6": 48.01986752084175, "rsi12": 50.979035956256844, "kd_k": 30.1485056052559, "kd_d": 38.11181007495783, "macd_osc": -0.6733835124701146}, {"date": "2025-06-04", "taiex": 21618.09, "high": 119.0, "low": 116.5, "close": 118.5, "lots": 4688, "change_pct": 2.1551724137931036, "ma5": 116.4, "ma10": 117.3, "ma20": 116.275, "ma60": null, "rsi6": 59.89600515081302, "rsi12": 56.79596757642704, "kd_k": 43.01567040350393, "kd_d": 39.7464301844732, "macd_osc": -0.4856599871294214}, {"date": "2025-06-05", "taiex": 21674.43, "high": 120.5, "low": 117.0, "close": 120.0, "lots": 5770, "change_pct": 1.2658227848101267, "ma5": 117.0, "ma10": 117.45, "ma20": 116.9, "ma60": null, "rsi6": 65.5612391505323, "rsi12": 59.90976612474263, "kd_k": 57.84378026900262, "kd_d": 45.77888021264967, "macd_osc": -0.26545527889007703}, {"date": "2025-06-06", "taiex": 21660.66, "high": 125.0, "low": 120.0, "close": 125.0, "lots": 9458, "change_pct": 4.166666666666666, "ma5": 118.6, "ma10": 118.15, "ma20": 117.6, "ma60": null, "rsi6": 77.99516594604783, "rsi12": 68.23478662490011, "kd_k": 71.89585351266841, "kd_d": 54.48453797932258, "macd_osc": 0.18753136048662444}, {"date": "2025-06-09", "taiex": 21790.29, "high": 126.0, "low": 122.0, "close": 126.0, "lots": 5356, "change_pct": 0.8, "ma5": 121.1, "ma10": 118.8, "ma20": 118.2, "ma60": null, "rsi6": 79.749855006216, "rsi12": 69.61159404478094, "kd_k": 81.26390234177893, "kd_d": 63.41099276680803, "macd_osc": 0.5069768192288229}, {"date": "2025-06-10", "taiex": 22242.14, "high": 129.0, "low": 126.0, "close": 129.0, "lots": 7176, "change_pct": 2.380952380952381, "ma5": 123.7, "ma10": 119.85, "ma20": 118.925, "ma60": null, "rsi6": 84.26645118983839, "rsi12": 73.3867062475885, "kd_k": 87.50926822785262, "kd_d": 71.44375125382288, "macd_osc": 0.8524552191794763}, {"date": "2025-06-11", "taiex": 22470.1, "high": 131.0, "low": 126.5, "close": 130.0, "lots": 11349, "change_pct": 0.7751937984496124, "ma5": 126.0, "ma10": 121.2, "ma20": 119.675, "ma60": null, "rsi6": 85.55516287559041, "rsi12": 74.5369748103083, "kd_k": 89.82099363338322, "kd_d": 77.56949871367632, "macd_osc": 1.0665617682225284}, {"date": "2025-06-12", "taiex": 22287.82, "high": 130.0, "low": 127.0, "close": 130.0, "lots": 6760, "change_pct": 0.0, "ma5": 128.0, "ma10": 122.5, "ma20": 120.175, "ma60": null, "rsi6": 85.55516287559041, "rsi12": 74.5369748103083, "kd_k": 91.36214390373696, "kd_d": 82.1670471103632, "macd_osc": 1.1208545932865497}, {"date": "2025-06-13", "taiex": 22072.95, "high": 130.5, "low": 128.0, "close": 129.5, "lots": 5131, "change_pct": -0.38461538461538464, "ma5": 128.9, "ma10": 123.75, "ma20": 120.675, "ma60": null, "rsi6": 80.7906068140985, "rsi12": 72.66805240852574, "kd_k": 91.30025279856974, "kd_d": 85.21144900643205, "macd_osc": 1.037669666409827}, {"date": "2025-06-16", "taiex": 22049.9, "high": 133.0, "low": 128.0, "close": 132.0, "lots": 5282, "change_pct": 1.9305019305019304, "ma5": 130.1, "ma10": 125.6, "ma20": 121.35, "ma60": null, "rsi6": 85.60165780810475, "rsi12": 75.956398993655, "kd_k": 92.1799665121778, "kd_d": 87.53428817501396, "macd_osc": 1.0617649717110118}, {"date": "2025-06-17", "taiex": 22211.59, "high": 134.0, "low": 132.0, "close": 132.0, "lots": 4151, "change_pct": 0.0, "ma5": 130.7, "ma10": 127.2, "ma20": 122.15, "ma60": null, "rsi6": 85.60165780810475, "rsi12": 75.956398993655, "kd_k": 90.86507571400088, "kd_d": 88.64455068800959, "macd_osc": 0.9898741957706743}, {"date": "2025-06-18", "taiex": 22356.73, "high": 134.5, "low": 132.5, "close": 133.0, "lots": 3132, "change_pct": 0.7575757575757576, "ma5": 131.3, "ma10": 128.65, "ma20": 122.975, "ma60": null, "rsi6": 87.41690682455587, "rsi12": 77.25883623150888, "kd_k": 90.46177461393162, "kd_d": 89.25029199665026, "macd_osc": 0.9231513772307776}, {"date": "2025-06-19", "taiex": 22003.5, "high": 134.0, "low": 129.5, "close": 130.0, "lots": 4045, "change_pct": -2.2556390977443606, "ma5": 131.3, "ma10": 129.65, "ma20": 123.55, "ma60": null, "rsi6": 60.127272171985545, "rsi12": 65.62469331187057, "kd_k": 81.64118307595442, "kd_d": 86.71392235641831, "macd_osc": 0.6057907506778948}, {"date": "2025-06-20", "taiex": 22045.74, "high": 131.0, "low": 128.0, "close": 130.5, "lots": 5969, "change_pct": 0.38461538461538464, "ma5": 131.5, "ma10": 130.2, "ma20": 124.175, "ma60": null, "rsi6": 62.470451978686384, "rsi12": 66.54078571446357, "kd_k": 72.07451420749902, "kd_d": 81.83411964011188, "macd_osc": 0.3699528738833555}, {"date": "2025-06-23", "taiex": 21732.02, "high": 130.0, "low": 127.0, "close": 128.5, "lots": 3367, "change_pct": -1.532567049808429, "ma5": 130.8, "ma10": 130.45, "ma20": 124.625, "ma60": null, "rsi6": 48.72589539194366, "rsi12": 59.60888619042407, "kd_k": 56.383009471666014, "kd_d": 73.35041625062992, "macd_osc": 0.037187531506872595}, {"date": "2025-06-24", "taiex": 22188.76, "high": 134.0, "low": 130.5, "close": 133.0, "lots": 4140, "change_pct": 3.501945525291829, "ma5": 131.0, "ma10": 130.85, "ma20": 125.35, "ma60": null, "rsi6": 67.8339805990168, "rsi12": 67.83385754930983, "kd_k": 64.25533964777733, "kd_d": 70.31872404967905, "macd_osc": 0.07584409752500854}, {"date": "2025-06-25", "taiex": 22430.61, "high": 134.5, "low": 131.5, "close": 132.0, "lots": 2599, "change_pct": -0.7518796992481203, "ma5": 130.8, "ma10": 131.05, "ma20": 126.125, "ma60": null, "rsi6": 61.70217613105521, "rsi12": 64.64272903220946, "kd_k": 65.05911532074043, "kd_d": 68.56552114003284, "macd_osc": -0.0058957360179521245}, {"date": "2025-06-26", "taiex": 22492.34, "high": 134.0, "low": 131.5, "close": 131.5, "lots": 3180, "change_pct": -0.3787878787878788, "ma5": 131.1, "ma10": 131.2, "ma20": 126.85, "ma60": null, "rsi6": 58.52782731758247, "rsi12": 63.02549594891061, "kd_k": 63.37274354716028, "kd_d": 66.83459527574198, "macd_osc": -0.1268904937131916}, {"date": "2025-06-27", "taiex": 22580.08, "high": 133.5, "low": 131.0, "close": 132.0, "lots": 3644, "change_pct": 0.38022813688212925, "ma5": 131.4, "ma10": 131.45, "ma20": 127.6, "ma60": null, "rsi6": 60.93926385136254, "rsi12": 64.00780870438105, "kd_k": 64.47071792032907, "kd_d": 66.046636157271, "macd_osc": -0.20203985931989443}, {"date": "2025-06-30", "taiex": 22256.02, "high": 133.5, "low": 131.0, "close": 131.5, "lots": 2894, "change_pct": -0.3787878787878788, "ma5": 132.0, "ma10": 131.4, "ma20": 128.5, "ma60": null, "rsi6": 56.96455772680191, "rsi12": 62.20495306110469, "kd_k": 62.980478613552705, "kd_d": 65.02458364269823, "macd_osc": -0.30787194152460273}, {"date": "2025-07-01", "taiex": 22553.72, "high": 133.5, "low": 131.0, "close": 131.5, "lots": 5105, "change_pct": 0.0, "ma5": 131.7, "ma10": 131.35, "ma20": 129.275, "ma60": null, "rsi6": 56.96455772680191, "rsi12": 62.204953061104696, "kd_k": 61.98698574236847, "kd_d": 64.01205100925498, "macd_osc": -0.3947769291019254}, {"date": "2025-07-02", "taiex": 22577.74, "high": 132.5, "low": 131.0, "close": 132.5, "lots": 3099, "change_pct": 0.7604562737642585, "ma5": 131.8, "ma10": 131.3, "ma20": 129.975, "ma60": null, "rsi6": 63.77016210250661, "rsi12": 64.57954632298521, "kd_k": 65.76910160602341, "kd_d": 64.59773454151112, "macd_osc": -0.40054563709878943}, {"date": "2025-07-03", "taiex": 22712.97, "high": 138.0, "low": 132.5, "close": 136.5, "lots": 6185, "change_pct": 3.018867924528302, "ma5": 132.8, "ma10": 131.95, "ma20": 130.8, "ma60": null, "rsi6": 79.40397839854916, "rsi12": 72.20092085352977, "kd_k": 72.63394652522773, "kd_d": 67.27647186941665, "macd_osc": -0.16279137573806324}, {"date": "2025-07-04", "taiex": 22547.5, "high": 137.0, "low": 133.0, "close": 134.5, "lots": 4503, "change_pct": -1.465201465201465, "ma5": 133.3, "ma10": 132.35, "ma20": 131.275, "ma60": null, "rsi6": 63.073563097365344, "rsi12": 64.617144576546, "kd_k": 66.20040879459626, "kd_d": 66.91778417780985, "macd_osc": -0.1674000546900718}, {"date": "2025-07-07", "taiex": 22428.72, "high": 134.5, "low": 131.5, "close": 133.0, "lots": 5155, "change_pct": -1.1152416356877324, "ma5": 133.6, "ma10": 132.8, "ma20": 131.625, "ma60": null, "rsi6": 53.22231536774779, "rsi12": 59.503450415919126, "kd_k": 53.657415386873694, "kd_d": 62.497661247497796, "macd_osc": -0.2913851642185663}, {"date": "2025-07-08", "taiex": 22362.27, "high": 135.0, "low": 132.0, "close": 134.0, "lots": 4049, "change_pct": 0.7518796992481203, "ma5": 134.1, "ma10": 132.9, "ma20": 131.875, "ma60": 120.66666666666667, "rsi6": 58.4179622855535, "rsi12": 61.70738795004084, "kd_k": 50.05732454363008, "kd_d": 58.35088234620856, "macd_osc": -0.3234853181348507}, {"date": "2025-07-09", "taiex": 22527.01, "high": 136.5, "low": 132.5, "close": 136.5, "lots": 4055, "change_pct": 1.8656716417910446, "ma5": 134.9, "ma10": 133.35, "ma20": 132.2, "ma60": 121.05, "rsi6": 68.81066093888924, "rsi12": 66.65643775806035, "kd_k": 59.56202588622958, "kd_d": 58.7545968595489, "macd_osc": -0.19984723466865928}, {"date": "2025-07-10", "taiex": 22693.25, "high": 137.5, "low": 135.0, "close": 135.5, "lots": 4628, "change_pct": -0.7326007326007326, "ma5": 134.7, "ma10": 133.75, "ma20": 132.475, "ma60": 121.39166666666667, "rsi6": 61.439870016863324, "rsi12": 63.09790998877979, "kd_k": 61.13658868605781, "kd_d": 59.548594135051864, "macd_osc": -0.20798308488877515}, {"date": "2025-07-11", "taiex": 22751.03, "high": 137.0, "low": 135.0, "close": 136.0, "lots": 2623, "change_pct": 0.36900369003690037, "ma5": 135.0, "ma10": 134.15, "ma20": 132.8, "ma60": 121.80833333333334, "rsi6": 63.76847703980707, "rsi12": 64.1420816399135, "kd_k": 64.56724960022902, "kd_d": 61.221479290110906, "macd_osc": -0.20208525789814313}, {"date": "2025-07-14", "taiex": 22614.97, "high": 137.5, "low": 136.0, "close": 136.5, "lots": 2029, "change_pct": 0.3676470588235294, "ma5": 135.7, "ma10": 134.65, "ma20": 133.025, "ma60": 122.225, "rsi6": 66.21664776846407, "rsi12": 65.21580272262719, "kd_k": 69.23530925729554, "kd_d": 63.89275594583911, "macd_osc": -0.18723997456549712}, {"date": "2025-07-15", "taiex": 22835.94, "high": 137.0, "low": 135.5, "close": 136.5, "lots": 3198, "change_pct": 0.0, "ma5": 136.2, "ma10": 135.15, "ma20": 133.25, "ma60": 122.65833333333333, "rsi6": 66.21664776846407, "rsi12": 65.21580272262719, "kd_k": 71.79789847922267, "kd_d": 66.52780345696696, "macd_osc": -0.19904688735368614}, {"date": "2025-07-16", "taiex": 23042.9, "high": 141.5, "low": 137.0, "close": 138.5, "lots": 8451, "change_pct": 1.465201465201465, "ma5": 136.6, "ma10": 135.75, "ma20": 133.525, "ma60": 123.13333333333334, "rsi6": 75.68150847714017, "rsi12": 69.55543816625081, "kd_k": 71.19859898614844, "kd_d": 68.08473530002745, "macd_osc": -0.0988509466985974}, {"date": "2025-07-17", "taiex": 23113.28, "high": 140.5, "low": 138.5, "close": 139.5, "lots": 5204, "change_pct": 0.7220216606498195, "ma5": 137.4, "ma10": 136.05, "ma20": 134.0, "ma60": 123.63333333333334, "rsi6": 79.18112179503288, "rsi12": 71.49519755569764, "kd_k": 74.13239932409896, "kd_d": 70.10062330805128, "macd_osc": 0.0027014133491833903}, {"date": "2025-07-18", "taiex": 23383.13, "high": 140.0, "low": 138.0, "close": 138.5, "lots": 4474, "change_pct": -0.7168458781362007, "ma5": 137.9, "ma10": 136.45, "ma20": 134.4, "ma60": 124.0, "rsi6": 67.5209896214105, "rsi12": 66.84876053491058, "kd_k": 72.22861709325895, "kd_d": 70.80995456978717, "macd_osc": -0.027861076429726683}, {"date": "2025-07-21", "taiex": 23340.56, "high": 140.0, "low": 137.5, "close": 139.0, "lots": 3663, "change_pct": 0.36101083032490977, "ma5": 138.4, "ma10": 137.05, "ma20": 134.925, "ma60": 124.41666666666667, "rsi6": 70.15771638244911, "rsi12": 67.98370048574927, "kd_k": 72.22648546958004, "kd_d": 71.28213153638478, "macd_osc": -0.04383846161833649}, {"date": "2025-07-22", "taiex": 22987.92, "high": 140.0, "low": 136.5, "close": 137.0, "lots": 5127, "change_pct": -1.4388489208633095, "ma5": 138.5, "ma10": 137.35, "ma20": 135.125, "ma60": 124.84166666666667, "rsi6": 50.48494764655568, "rsi12": 59.14763280809225, "kd_k": 58.40740056946361, "kd_d": 66.99055454741105, "macd_osc": -0.20928086769969312}, {"date": "2025-07-23", "taiex": 23318.67, "high": 140.0, "low": 137.5, "close": 139.0, "lots": 3359, "change_pct": 1.4598540145985401, "ma5": 138.6, "ma10": 137.6, "ma20": 135.475, "ma60": 125.3, "rsi6": 62.95140447115566, "rsi12": 64.22074111876744, "kd_k": 59.45108755912958, "kd_d": 64.47739888465055, "macd_osc": -0.20398464024930574}, {"date": "2025-07-24", "taiex": 23373.73, "high": 139.0, "low": 138.0, "close": 139.0, "lots": 2276, "change_pct": 0.0, "ma5": 138.5, "ma10": 137.95, "ma20": 135.85, "ma60": 125.75833333333334, "rsi6": 62.951404471155655, "rsi12": 64.22074111876744, "kd_k": 59.078502817197496, "kd_d": 62.677766862166195, "macd_osc": -0.21912078743112318}, {"date": "2025-07-25", "taiex": 23364.38, "high": 140.0, "low": 137.5, "close": 140.0, "lots": 4638, "change_pct": 0.7194244604316548, "ma5": 138.8, "ma10": 138.35, "ma20": 136.25, "ma60": 126.28333333333333, "rsi6": 68.63677755872783, "rsi12": 66.68266324954197, "kd_k": 64.38566854479834, "kd_d": 63.247067423043575, "macd_osc": -0.18195300492915312}, {"date": "2025-07-28", "taiex": 23412.98, "high": 141.0, "low": 139.0, "close": 141.0, "lots": 6134, "change_pct": 0.7142857142857143, "ma5": 139.2, "ma10": 138.8, "ma20": 136.725, "ma60": 126.81666666666666, "rsi6": 73.51411644095177, "rsi12": 69.00897280129622, "kd_k": 72.92377902986556, "kd_d": 66.47263795865089, "macd_osc": -0.11353582146894992}, {"date": "2025-07-29", "taiex": 23201.52, "high": 141.0, "low": 138.0, "close": 139.0, "lots": 5257, "change_pct": -1.4184397163120568, "ma5": 139.6, "ma10": 139.05, "ma20": 137.1, "ma60": 127.375, "rsi6": 53.53382662660551, "rsi12": 59.885914177489106, "kd_k": 67.13437120509556, "kd_d": 66.69321570746578, "macd_osc": -0.2203128810505799}, {"date": "2025-07-30", "taiex": 23461.72, "high": 139.0, "low": 137.0, "close": 139.0, "lots": 6867, "change_pct": 0.0, "ma5": 139.6, "ma10": 139.1, "ma20": 137.425, "ma60": 127.89166666666667, "rsi6": 53.5338266266055, "rsi12": 59.885914177489106, "kd_k": 63.274765988582224, "kd_d": 65.55373246783793, "macd_osc": -0.3031634029343695}, {"date": "2025-07-31", "taiex": 23542.52, "high": 132.0, "low": 124.5, "close": 126.0, "lots": 13170, "change_pct": -9.352517985611511, "ma5": 137.0, "ma10": 137.75, "ma20": 136.9, "ma60": 128.2, "rsi6": 15.105736640029505, "rsi12": 29.607707032887276, "kd_k": 45.21348035602451, "kd_d": 58.773648430566794, "macd_osc": -1.1956127321727843}, {"date": "2025-08-01", "taiex": 23434.38, "high": 124.5, "low": 122.0, "close": 123.5, "lots": 9740, "change_pct": -1.984126984126984, "ma5": 133.7, "ma10": 136.25, "ma20": 136.35, "ma60": 128.40833333333333, "rsi6": 12.959037594912687, "rsi12": 26.768395598547613, "kd_k": 32.77389918471809, "kd_d": 50.107065348617226, "macd_osc": -1.8759087274347914}, {"date": "2025-08-04", "taiex": 23378.94, "high": 123.5, "low": 121.0, "close": 122.5, "lots": 3908, "change_pct": -0.8097165991902834, "ma5": 130.0, "ma10": 134.6, "ma20": 135.825, "ma60": 128.55, "rsi6": 12.131504884985787, "rsi12": 25.693229635482282, "kd_k": 24.34926612314539, "kd_d": 41.52113227345994, "macd_osc": -2.287566811672378}, {"date": "2025-08-05", "taiex": 23660.59, "high": 123.5, "low": 121.0, "close": 122.5, "lots": 5481, "change_pct": 0.0, "ma5": 126.7, "ma10": 133.15, "ma20": 135.25, "ma60": 128.68333333333334, "rsi6": 12.131504884985787, "rsi12": 25.693229635482297, "kd_k": 18.732844082096925, "kd_d": 33.92503620967227, "macd_osc": -2.440236569343893}, {"date": "2025-08-06", "taiex": 23447.36, "high": 123.0, "low": 120.0, "close": 120.0, "lots": 4061, "change_pct": -2.0408163265306123, "ma5": 122.9, "ma10": 131.25, "ma20": 134.425, "ma60": 128.76666666666668, "rsi6": 9.863916145163572, "rsi12": 22.950615934734856, "kd_k": 12.48856272139795, "kd_d": 26.779545046914162, "macd_osc": -2.5765566271830815}, {"date": "2025-08-07", "taiex": 24003.77, "high": 123.0, "low": 120.5, "close": 122.0, "lots": 4544, "change_pct": 1.6666666666666667, "ma5": 122.1, "ma10": 129.55, "ma20": 133.75, "ma60": 128.8, "rsi6": 23.577262302027506, "rsi12": 29.516759213211927, "kd_k": 11.500311655535139, "kd_d": 21.686467249787817, "macd_osc": -2.402430906306848}, {"date": "2025-08-08", "taiex": 24021.26, "high": 124.5, "low": 122.0, "close": 122.0, "lots": 3609, "change_pct": 0.0, "ma5": 121.8, "ma10": 127.75, "ma20": 133.05, "ma60": 128.84166666666667, "rsi6": 23.577262302027506, "rsi12": 29.516759213211927, "kd_k": 10.8414776116266, "kd_d": 18.07147070373408, "macd_osc": -2.1650114453214435}, {"date": "2025-08-11", "taiex": 24135.5, "high": 122.5, "low": 120.0, "close": 121.0, "lots": 2779, "change_pct": -0.819672131147541, "ma5": 121.5, "ma10": 125.75, "ma20": 132.275, "ma60": 128.88333333333333, "rsi6": 21.249561180612474, "rsi12": 28.092220117738393, "kd_k": 8.98203770599668, "kd_d": 15.041659704488278, "macd_osc": -1.9592497794980344}, {"date": "2025-08-12", "taiex": 24158.36, "high": 122.5, "low": 121.0, "close": 121.5, "lots": 1633, "change_pct": 0.4132231404958678, "ma5": 121.3, "ma10": 124.0, "ma20": 131.525, "ma60": 128.975, "rsi6": 25.653541569314214, "rsi12": 29.936621093631615, "kd_k": 10.154691803997785, "kd_d": 13.412670404324778, "macd_osc": -1.6839249506067948}, {"date": "2025-08-13", "taiex": 24370.02, "high": 124.0, "low": 122.0, "close": 123.0, "lots": 2981, "change_pct": 1.2345679012345678, "ma5": 121.9, "ma10": 122.4, "ma20": 130.75, "ma60": 129.08333333333334, "rsi6": 38.1128844103471, "rsi12": 35.36254301936792, "kd_k": 28.992016758220743, "kd_d": 18.60578585562343, "macd_osc": -1.3117765918471722}, {"date": "2025-08-14", "taiex": 24238.1, "high": 124.0, "low": 122.5, "close": 123.5, "lots": 1711, "change_pct": 0.40650406504065045, "ma5": 122.2, "ma10": 122.15, "ma20": 129.95, "ma60": 129.16666666666666, "rsi6": 42.000800153209134, "rsi12": 37.13294895744419, "kd_k": 45.25393709807309, "kd_d": 27.488502936439982, "macd_osc": -0.9592776118814141}, {"date": "2025-08-15", "taiex": 24334.48, "high": 123.5, "low": 121.0, "close": 122.0, "lots": 1961, "change_pct": -1.214574898785425, "ma5": 122.2, "ma10": 122.0, "ma20": 129.125, "ma60": 129.23333333333332, "rsi6": 34.25388297143844, "rsi12": 34.078203010733276, "kd_k": 44.984106213530204, "kd_d": 33.320370695470054, "macd_osc": -0.7630220007946225}, {"date": "2025-08-18", "taiex": 24482.52, "high": 122.5, "low": 121.0, "close": 122.0, "lots": 1734, "change_pct": 0.0, "ma5": 122.4, "ma10": 121.95, "ma20": 128.275, "ma60": 129.275, "rsi6": 34.25388297143844, "rsi12": 34.078203010733276, "kd_k": 44.80421895716828, "kd_d": 37.148320116036125, "macd_osc": -0.5775191726045037}, {"date": "2025-08-19", "taiex": 24353.5, "high": 122.0, "low": 120.0, "close": 120.0, "lots": 2001, "change_pct": -1.639344262295082, "ma5": 122.1, "ma10": 121.7, "ma20": 127.425, "ma60": 129.3, "rsi6": 25.29570988566155, "rsi12": 30.143393936472492, "kd_k": 29.869479304778853, "kd_d": 34.72203984561703, "macd_osc": -0.5347993898214609}, {"date": "2025-08-20", "taiex": 23625.44, "high": 120.0, "low": 116.5, "close": 116.5, "lots": 3211, "change_pct": -2.9166666666666665, "ma5": 120.8, "ma10": 121.35, "ma20": 126.3, "ma60": 129.3, "rsi6": 16.328261554093515, "rsi12": 24.698964905084466, "kd_k": 19.912986203185902, "kd_d": 29.78568863147332, "macd_osc": -0.6783202750752046}, {"date": "2025-08-21", "taiex": 23962.13, "high": 119.5, "low": 117.5, "close": 119.5, "lots": 2596, "change_pct": 2.575107296137339, "ma5": 120.0, "ma10": 121.1, "ma20": 125.325, "ma60": 129.34166666666667, "rsi6": 38.68555659025979, "rsi12": 35.57898133034192, "kd_k": 26.6086574687906, "kd_d": 28.726678243912414, "macd_osc": -0.5146887570792584}, {"date": "2025-08-22", "taiex": 23764.47, "high": 119.5, "low": 116.0, "close": 117.0, "lots": 1862, "change_pct": -2.092050209205021, "ma5": 119.0, "ma10": 120.6, "ma20": 124.175, "ma60": 129.34166666666667, "rsi6": 30.528315371297055, "rsi12": 31.44820414436539, "kd_k": 21.905771645860398, "kd_d": 26.453042711228406, "macd_osc": -0.5169419690278478}, {"date": "2025-08-25", "taiex": 24277.38, "high": 120.0, "low": 118.0, "close": 118.5, "lots": 1256, "change_pct": 1.282051282051282, "ma5": 118.3, "ma10": 120.35, "ma20": 123.05, "ma60": 129.425, "rsi6": 39.68525677514736, "rsi12": 36.289784514106366, "kd_k": 25.0205144305736, "kd_d": 25.975533284343467, "macd_osc": -0.36660152830613146}, {"date": "2025-08-26", "taiex": 24305.1, "high": 120.5, "low": 118.5, "close": 118.5, "lots": 3380, "change_pct": 0.0, "ma5": 118.0, "ma10": 120.05, "ma20": 122.025, "ma60": 129.46666666666667, "rsi6": 39.68525677514736, "rsi12": 36.289784514106366, "kd_k": 27.097009620382394, "kd_d": 26.349358729689772, "macd_osc": -0.2233903733370175}, {"date": "2025-08-27", "taiex": 24519.9, "high": 120.0, "low": 119.0, "close": 119.5, "lots": 1287, "change_pct": 0.8438818565400843, "ma5": 118.6, "ma10": 119.7, "ma20": 121.05, "ma60": 129.48333333333332, "rsi6": 46.45999121281486, "rsi12": 39.67031774675366, "kd_k": 33.62022863581048, "kd_d": 28.772982031730006, "macd_osc": -0.027828266283386416}, {"date": "2025-08-28", "taiex": 24236.45, "high": 120.0, "low": 118.5, "close": 118.5, "lots": 2061, "change_pct": -0.8368200836820083, "ma5": 118.4, "ma10": 119.2, "ma20": 120.675, "ma60": 129.45833333333334, "rsi6": 40.94157352700896, "rsi12": 37.49965681484554, "kd_k": 35.2339985777198, "kd_d": 30.926654213726604, "macd_osc": 0.0627228131401294}, {"date": "2025-08-29", "taiex": 24233.1, "high": 120.5, "low": 118.0, "close": 119.0, "lots": 2299, "change_pct": 0.42194092827004215, "ma5": 118.8, "ma10": 118.9, "ma20": 120.45, "ma60": 129.35833333333332, "rsi6": 44.870473383615675, "rsi12": 39.310976170406065, "kd_k": 40.1559990518132, "kd_d": 34.003102493088804, "macd_osc": 0.17829171538263866}, {"date": "2025-09-01", "taiex": 24071.73, "high": 121.0, "low": 118.0, "close": 119.0, "lots": 2003, "change_pct": 0.0, "ma5": 118.9, "ma10": 118.6, "ma20": 120.275, "ma60": 129.24166666666667, "rsi6": 44.870473383615675, "rsi12": 39.310976170406065, "kd_k": 46.77066603454213, "kd_d": 38.25895700690658, "macd_osc": 0.2711677966753405}, {"date": "2025-09-02", "taiex": 24016.78, "high": 123.0, "low": 119.0, "close": 119.5, "lots": 4403, "change_pct": 0.42016806722689076, "ma5": 119.1, "ma10": 118.55, "ma20": 120.125, "ma60": 129.08333333333334, "rsi6": 49.69001533257104, "rsi12": 41.3343387683849, "kd_k": 47.84711068969475, "kd_d": 41.45500823450263, "macd_osc": 0.37624252542648096}, {"date": "2025-09-03", "taiex": 24100.3, "high": 121.0, "low": 118.0, "close": 119.5, "lots": 2456, "change_pct": 0.0, "ma5": 119.1, "ma10": 118.85, "ma20": 120.1, "ma60": 128.90833333333333, "rsi6": 49.69001533257104, "rsi12": 41.3343387683849, "kd_k": 48.5647404597965, "kd_d": 43.82491897626725, "macd_osc": 0.4506885744383031}, {"date": "2025-09-04", "taiex": 24179.85, "high": 121.5, "low": 119.0, "close": 120.0, "lots": 2117, "change_pct": 0.41841004184100417, "ma5": 119.4, "ma10": 118.9, "ma20": 120.0, "ma60": 128.74166666666667, "rsi6": 55.3152808477203, "rsi12": 43.57319471070773, "kd_k": 45.709826973197664, "kd_d": 44.453221641910716, "macd_osc": 0.5329161969429386}, {"date": "2025-09-05", "taiex": 24494.58, "high": 121.0, "low": 119.5, "close": 120.5, "lots": 2015, "change_pct": 0.4166666666666667, "ma5": 119.7, "ma10": 119.25, "ma20": 119.925, "ma60": 128.59166666666667, "rsi6": 60.60154948411253, "rsi12": 45.828481373267955, "kd_k": 47.13988464879844, "kd_d": 45.34877597753996, "macd_osc": 0.6144960273016551}, {"date": "2025-09-08", "taiex": 24547.38, "high": 128.5, "low": 123.0, "close": 126.5, "lots": 9501, "change_pct": 4.979253112033195, "ma5": 121.2, "ma10": 120.05, "ma20": 120.2, "ma60": 128.5, "rsi6": 85.42709546416363, "rsi12": 64.43623164030461, "kd_k": 58.41071674999261, "kd_d": 49.70275623502417, "macd_osc": 1.0409898748325985}, {"date": "2025-09-09", "taiex": 24855.18, "high": 127.0, "low": 125.0, "close": 126.0, "lots": 5001, "change_pct": -0.3952569169960474, "ma5": 122.5, "ma10": 120.8, "ma20": 120.425, "ma60": 128.4, "rsi6": 80.3632860340401, "rsi12": 62.485012558600445, "kd_k": 64.3373032301538, "kd_d": 54.580938566734034, "macd_osc": 1.2441241926867814}, {"date": "2025-09-10", "taiex": 25192.59, "high": 127.5, "low": 126.0, "close": 127.0, "lots": 3401, "change_pct": 0.7936507936507936, "ma5": 124.0, "ma10": 121.55, "ma20": 120.625, "ma60": 128.3, "rsi6": 82.80894296533401, "rsi12": 64.80996541281468, "kd_k": 71.46296405819777, "kd_d": 60.20828039722194, "macd_osc": 1.3895033329581894}, {"date": "2025-09-11", "taiex": 25215.71, "high": 134.0, "low": 129.0, "close": 129.5, "lots": 9119, "change_pct": 1.968503937007874, "ma5": 125.9, "ma10": 122.65, "ma20": 120.925, "ma60": 128.29166666666666, "rsi6": 87.48499240026632, "rsi12": 69.89783175114616, "kd_k": 71.60030937213185, "kd_d": 64.00562338885857, "macd_osc": 1.583621168626818}, {"date": "2025-09-12", "taiex": 25474.64, "high": 142.0, "low": 133.0, "close": 142.0, "lots": 24876, "change_pct": 9.652509652509652, "ma5": 130.2, "ma10": 124.95, "ma20": 121.925, "ma60": 128.48333333333332, "rsi6": 95.24510955651009, "rsi12": 83.17028709169244, "kd_k": 81.06687291475455, "kd_d": 69.69270656415722, "macd_osc": 2.4326787418344664}, {"date": "2025-09-15", "taiex": 25357.16, "high": 152.5, "low": 139.0, "close": 151.0, "lots": 34410, "change_pct": 6.338028169014084, "ma5": 135.1, "ma10": 128.15, "ma20": 123.375, "ma60": 128.85833333333332, "rsi6": 96.90383622673534, "rsi12": 87.49944810411496, "kd_k": 85.9286399141842, "kd_d": 75.10468434749954, "macd_osc": 3.4188244629568896}, {"date": "2025-09-16", "taiex": 25629.64, "high": 151.0, "low": 145.5, "close": 148.5, "lots": 24389, "change_pct": -1.6556291390728477, "ma5": 139.6, "ma10": 131.05, "ma20": 124.8, "ma60": 129.11666666666667, "rsi6": 86.8094469770657, "rsi12": 81.1721250753616, "kd_k": 86.63899377363524, "kd_d": 78.94945415621143, "macd_osc": 3.6975036647124613}, {"date": "2025-09-17", "taiex": 25438.25, "high": 151.0, "low": 143.0, "close": 145.0, "lots": 15467, "change_pct": -2.356902356902357, "ma5": 143.2, "ma10": 133.6, "ma20": 126.225, "ma60": 129.33333333333334, "rsi6": 73.88011917648342, "rsi12": 73.0989825112446, "kd_k": 83.51690493999924, "kd_d": 80.47193775080737, "macd_osc": 3.445902711183752}, {"date": "2025-09-18", "taiex": 25769.36, "high": 153.0, "low": 147.0, "close": 149.5, "lots": 22666, "change_pct": 3.103448275862069, "ma5": 147.2, "ma10": 136.55, "ma20": 127.725, "ma60": 129.63333333333333, "rsi6": 78.76073072596068, "rsi12": 76.39222555640126, "kd_k": 85.1223810711106, "kd_d": 82.02208552424177, "macd_osc": 3.3778091685195504}, {"date": "2025-09-19", "taiex": 25578.37, "high": 153.5, "low": 148.5, "close": 150.5, "lots": 14026, "change_pct": 0.6688963210702341, "ma5": 148.9, "ma10": 139.55, "ma20": 129.4, "ma60": 129.94166666666666, "rsi6": 79.76880674418545, "rsi12": 77.07265772598984, "kd_k": 86.57281545091583, "kd_d": 83.5389954997998, "macd_osc": 3.1972435581641796}, {"date": "2025-09-22", "taiex": 25880.6, "high": 152.5, "low": 149.5, "close": 151.0, "lots": 8525, "change_pct": 0.33222591362126247, "ma5": 148.9, "ma10": 142.0, "ma20": 131.025, "ma60": 130.26666666666668, "rsi6": 80.32899187913782, "rsi12": 77.4275262762676, "kd_k": 88.01824060364085, "kd_d": 85.03207720108014, "macd_osc": 2.916452185677614}, {"date": "2025-09-23", "taiex": 26247.37, "high": 153.0, "low": 148.5, "close": 150.5, "lots": 7772, "change_pct": -0.33112582781456956, "ma5": 149.3, "ma10": 144.45, "ma20": 132.625, "ma60": 130.58333333333334, "rsi6": 77.74573323415049, "rsi12": 76.14186702156054, "kd_k": 87.93052774936601, "kd_d": 85.99822738384209, "macd_osc": 2.517095946627922}, {"date": "2025-09-24", "taiex": 26196.73, "high": 151.5, "low": 148.0, "close": 151.0, "lots": 7720, "change_pct": 0.33222591362126247, "ma5": 150.5, "ma10": 146.85, "ma20": 134.2, "ma60": 130.89166666666668, "rsi6": 78.57261972731779, "rsi12": 76.56634876753567, "kd_k": 87.8886445158375, "kd_d": 86.62836642784056, "macd_osc": 2.122441153154673}, {"date": "2025-09-25", "taiex": 26023.85, "high": 150.5, "low": 148.5, "close": 150.5, "lots": 5064, "change_pct": -0.33112582781456956, "ma5": 150.7, "ma10": 148.95, "ma20": 135.8, "ma60": 131.125, "rsi6": 75.21879600773096, "rsi12": 75.10854037154594, "kd_k": 85.0292112864204, "kd_d": 86.09531471403383, "macd_osc": 1.6827664545651642}, {"date": "2025-09-26", "taiex": 25580.32, "high": 149.5, "low": 138.5, "close": 140.0, "lots": 13810, "change_pct": -6.976744186046512, "ma5": 148.6, "ma10": 148.75, "ma20": 136.85, "ma60": 131.21666666666667, "rsi6": 36.23873266652157, "rsi12": 52.297273217731146, "kd_k": 60.01947419094694, "kd_d": 77.40336787300487, "macd_osc": 0.5959106225421085}, {"date": "2025-09-30", "taiex": 25820.54, "high": 146.0, "low": 141.0, "close": 146.0, "lots": 7061, "change_pct": 4.285714285714286, "ma5": 147.6, "ma10": 148.25, "ma20": 138.2, "ma60": 131.43333333333334, "rsi6": 52.95595211789097, "rsi12": 59.89096277002777, "kd_k": 56.67964946063129, "kd_d": 70.495461735547, "macd_osc": 0.2120222248660646}, {"date": "2025-10-01", "taiex": 25982.91, "high": 148.0, "low": 145.0, "close": 147.0, "lots": 5961, "change_pct": 0.684931506849315, "ma5": 146.9, "ma10": 148.1, "ma20": 139.575, "ma60": 131.65, "rsi6": 55.29988791012959, "rsi12": 61.01919309487656, "kd_k": 56.675321862643074, "kd_d": 65.88874844457902, "macd_osc": -0.030707300178355545}, {"date": "2025-10-02", "taiex": 26378.39, "high": 155.5, "low": 149.5, "close": 151.0, "lots": 14625, "change_pct": 2.7210884353741496, "ma5": 146.9, "ma10": 148.7, "ma20": 141.15, "ma60": 131.89166666666668, "rsi6": 63.926985346245196, "rsi12": 65.28080354483006, "kd_k": 62.29335182999734, "kd_d": 64.69028290638512, "macd_osc": 0.019286083836806966}, {"date": "2025-10-03", "taiex": 26761.06, "high": 152.5, "low": 149.5, "close": 152.0, "lots": 5458, "change_pct": 0.6622516556291391, "ma5": 147.2, "ma10": 148.95, "ma20": 142.75, "ma60": 132.16666666666666, "rsi6": 65.9012948376162, "rsi12": 66.2860243356916, "kd_k": 67.99948945529235, "kd_d": 65.79335175602085, "macd_osc": 0.058634832125918024}, {"date": "2025-10-07", "taiex": 27211.95, "high": 160.0, "low": 153.5, "close": 158.0, "lots": 11749, "change_pct": 3.9473684210526314, "ma5": 150.8, "ma10": 149.7, "ma20": 144.625, "ma60": 132.53333333333333, "rsi6": 75.54004853198282, "rsi12": 71.65725203300497, "kd_k": 75.56555110972977, "kd_d": 69.05075154059048, "macd_osc": 0.4082036810020888}, {"date": "2025-10-08", "taiex": 27063.68, "high": 160.0, "low": 154.5, "close": 158.0, "lots": 7116, "change_pct": 0.0, "ma5": 153.2, "ma10": 150.4, "ma20": 146.2, "ma60": 132.89166666666668, "rsi6": 75.54004853198282, "rsi12": 71.65725203300497, "kd_k": 80.60959221268806, "kd_d": 72.90369843128967, "macd_osc": 0.5500511406048041}, {"date": "2025-10-09", "taiex": 27301.92, "high": 162.0, "low": 158.0, "close": 159.0, "lots": 10137, "change_pct": 0.6329113924050633, "ma5": 155.6, "ma10": 151.25, "ma20": 147.85, "ma60": 133.26666666666668, "rsi6": 77.09402024510779, "rsi12": 72.52545249827442, "kd_k": 82.8177423261892, "kd_d": 76.20837972958951, "macd_osc": 0.6168309654231017}, {"date": "2025-10-13", "taiex": 26923.42, "high": 156.0, "low": 149.0, "close": 153.5, "lots": 6811, "change_pct": -3.459119496855346, "ma5": 156.1, "ma10": 151.5, "ma20": 149.175, "ma60": 133.51666666666668, "rsi6": 54.31809665355283, "rsi12": 61.265308718994895, "kd_k": 76.48842396214032, "kd_d": 76.30172780710645, "macd_osc": 0.21683844493779514}, {"date": "2025-10-14", "taiex": 26793.15, "high": 156.5, "low": 147.0, "close": 147.5, "lots": 10016, "change_pct": -3.908794788273615, "ma5": 155.2, "ma10": 151.2, "ma20": 150.075, "ma60": 133.65, "rsi6": 39.16948148371894, "rsi12": 51.71073489242566, "kd_k": 61.30974295888719, "kd_d": 71.30439952436669, "macd_osc": -0.4871527204073782}, {"date": "2025-10-15", "taiex": 27275.71, "high": 151.0, "low": 147.0, "close": 150.0, "lots": 5318, "change_pct": 1.694915254237288, "ma5": 153.6, "ma10": 152.2, "ma20": 150.475, "ma60": 133.84166666666667, "rsi6": 46.6138369496505, "rsi12": 54.907277311948896, "kd_k": 50.67708354121891, "kd_d": 64.42862752998408, "macd_osc": -0.801219504699838}, {"date": "2025-10-16", "taiex": 27647.87, "high": 158.0, "low": 152.5, "close": 156.0, "lots": 7909, "change_pct": 4.0, "ma5": 153.2, "ma10": 153.2, "ma20": 150.725, "ma60": 134.125, "rsi6": 60.52634462551232, "rsi12": 61.56801714499742, "kd_k": 53.78472236081261, "kd_d": 60.880659140260256, "macd_osc": -0.6292373765525507}, {"date": "2025-10-17", "taiex": 27302.37, "high": 157.0, "low": 153.5, "close": 153.5, "lots": 4632, "change_pct": -1.6025641025641024, "ma5": 152.1, "ma10": 153.85, "ma20": 150.975, "ma60": 134.4, "rsi6": 53.54888765893659, "rsi12": 57.694313927500225, "kd_k": 50.300926018319515, "kd_d": 57.35408143294667, "macd_osc": -0.702640776952113}, {"date": "2025-10-20", "taiex": 27688.63, "high": 157.0, "low": 153.5, "close": 156.0, "lots": 3110, "change_pct": 1.6286644951140066, "ma5": 152.6, "ma10": 154.35, "ma20": 151.525, "ma60": 134.68333333333334, "rsi6": 59.19383331859106, "rsi12": 60.41155506485848, "kd_k": 53.53395067887968, "kd_d": 56.080704514924335, "macd_osc": -0.6053093656461934}, {"date": "2025-10-21", "taiex": 27752.41, "high": 158.0, "low": 152.0, "close": 152.0, "lots": 4200, "change_pct": -2.564102564102564, "ma5": 153.5, "ma10": 154.35, "ma20": 151.65, "ma60": 134.9, "rsi6": 47.995248982417344, "rsi12": 54.321644797974855, "kd_k": 46.80041156369756, "kd_d": 52.987273531182076, "macd_osc": -0.8195021477884561}, {"date": "2025-10-22", "taiex": 27648.91, "high": 153.0, "low": 150.0, "close": 151.5, "lots": 3083, "change_pct": -0.3289473684210526, "ma5": 153.8, "ma10": 153.7, "ma20": 151.7, "ma60": 135.09166666666667, "rsi6": 46.67083579265782, "rsi12": 53.58504256297949, "kd_k": 41.20027437579837, "kd_d": 49.05827381272084, "macd_osc": -0.9924942850559333}, {"date": "2025-10-23", "taiex": 27532.26, "high": 151.5, "low": 149.0, "close": 150.0, "lots": 2773, "change_pct": -0.9900990099009901, "ma5": 152.6, "ma10": 152.9, "ma20": 151.65, "ma60": 135.24166666666667, "rsi6": 42.45347290050847, "rsi12": 51.30808095626305, "kd_k": 36.557758674774675, "kd_d": 44.89143543340545, "macd_osc": -1.1921496911946008}, {"date": "2025-10-27", "taiex": 27993.63, "high": 164.5, "low": 156.0, "close": 160.5, "lots": 15322, "change_pct": 7.000000000000001, "ma5": 154.0, "ma10": 153.05, "ma20": 152.15, "ma60": 135.6, "rsi6": 67.28559080581914, "rsi12": 63.237177968984405, "kd_k": 50.08612483080216, "kd_d": 46.622998565871015, "macd_osc": -0.6295217352983631}, {"date": "2025-10-28", "taiex": 27949.11, "high": 176.5, "low": 161.5, "close": 176.5, "lots": 26686, "change_pct": 9.968847352024921, "ma5": 158.1, "ma10": 155.35, "ma20": 153.425, "ma60": 136.225, "rsi6": 81.71412696085557, "rsi12": 73.87627947846596, "kd_k": 66.72408322053477, "kd_d": 53.323360117425594, "macd_osc": 0.7338287352629136}, {"date": "2025-10-29", "taiex": 28294.74, "high": 185.5, "low": 175.0, "close": 182.0, "lots": 50000, "change_pct": 3.1161473087818696, "ma5": 164.1, "ma10": 158.8, "ma20": 155.0, "ma60": 137.15833333333333, "rsi6": 84.52881749542718, "rsi12": 76.43378836815606, "kd_k": 74.61970844839303, "kd_d": 60.42214289441473, "macd_osc": 1.855829466735198}, {"date": "2025-10-30", "taiex": 28287.53, "high": 185.0, "low": 175.0, "close": 177.0, "lots": 17060, "change_pct": -2.7472527472527473, "ma5": 169.2, "ma10": 161.5, "ma20": 156.85, "ma60": 138.05, "rsi6": 72.37549408551996, "rsi12": 69.66952017688453, "kd_k": 75.31724855463644, "kd_d": 65.38717811448862, "macd_osc": 2.0934244442699965}, {"date": "2025-10-31", "taiex": 28233.35, "high": 183.0, "low": 172.5, "close": 173.0, "lots": 14106, "change_pct": -2.2598870056497176, "ma5": 173.8, "ma10": 163.2, "ma20": 158.2, "ma60": 138.89166666666668, "rsi6": 63.597388913183806, "rsi12": 64.67439522009266, "kd_k": 72.12930725560236, "kd_d": 67.63455449485986, "macd_osc": 1.8232822337469745}, {"date": "2025-11-03", "taiex": 28334.59, "high": 176.0, "low": 169.5, "close": 173.0, "lots": 9922, "change_pct": 0.0, "ma5": 176.3, "ma10": 165.15, "ma20": 159.5, "ma60": 139.73333333333332, "rsi6": 63.597388913183806, "rsi12": 64.67439522009266, "kd_k": 70.00401305624632, "kd_d": 68.424374015322, "macd_osc": 1.500176517565576}, {"date": "2025-11-04", "taiex": 28116.56, "high": 180.5, "low": 174.0, "close": 174.0, "lots": 22428, "change_pct": 0.5780346820809248, "ma5": 175.8, "ma10": 166.95, "ma20": 160.65, "ma60": 140.63333333333333, "rsi6": 65.12033337016712, "rsi12": 65.41220356362818, "kd_k": 69.50039226580805, "kd_d": 68.78304676548402, "macd_osc": 1.2212104957398289}, {"date": "2025-11-05", "taiex": 27717.06, "high": 175.0, "low": 165.5, "close": 172.5, "lots": 15981, "change_pct": -0.8620689655172413, "ma5": 173.9, "ma10": 169.0, "ma20": 161.675, "ma60": 141.475, "rsi6": 60.559870036839214, "rsi12": 63.250492295245095, "kd_k": 67.7947820584839, "kd_d": 68.45362519648397, "macd_osc": 0.8222066937524026}, {"date": "2025-11-06", "taiex": 27899.45, "high": 174.5, "low": 167.0, "close": 170.0, "lots": 13098, "change_pct": -1.4492753623188406, "ma5": 172.5, "ma10": 170.85, "ma20": 162.275, "ma60": 142.275, "rsi6": 53.11977360967392, "rsi12": 59.66541220143384, "kd_k": 61.01573041187062, "kd_d": 65.97432693494618, "macd_osc": 0.303190336112535}, {"date": "2025-11-07", "taiex": 27651.41, "high": 173.0, "low": 166.0, "close": 170.0, "lots": 10690, "change_pct": 0.0, "ma5": 171.9, "ma10": 172.85, "ma20": 162.875, "ma60": 143.09166666666667, "rsi6": 53.11977360967392, "rsi12": 59.66541220143384, "kd_k": 52.4827091634693, "kd_d": 61.47712101112055, "macd_osc": -0.10498674384028917}, {"date": "2025-11-10", "taiex": 27869.51, "high": 173.0, "low": 164.5, "close": 172.0, "lots": 15523, "change_pct": 1.1764705882352942, "ma5": 171.7, "ma10": 174.0, "ma20": 163.525, "ma60": 143.93333333333334, "rsi6": 58.9320837110758, "rsi12": 61.73057366965518, "kd_k": 46.893234680408106, "kd_d": 56.615825567549734, "macd_osc": -0.29441998117960466}, {"date": "2025-11-11", "taiex": 27784.95, "high": 177.5, "low": 168.0, "close": 169.5, "lots": 15520, "change_pct": -1.4534883720930232, "ma5": 170.8, "ma10": 173.3, "ma20": 164.325, "ma60": 144.70833333333334, "rsi6": 49.69090727468921, "rsi12": 57.70187409165113, "kd_k": 39.39223775441841, "kd_d": 50.87462962983929, "macd_osc": -0.623326856903649}, {"date": "2025-11-12", "taiex": 27947.09, "high": 172.5, "low": 167.0, "close": 168.0, "lots": 8656, "change_pct": -0.8849557522123894, "ma5": 169.9, "ma10": 171.9, "ma20": 165.35, "ma60": 145.45, "rsi6": 44.64978393798406, "rsi12": 55.3379817315918, "kd_k": 32.56779814258525, "kd_d": 44.77235246742127, "macd_osc": -0.9571729133849463}, {"date": "2025-11-13", "taiex": 27903.56, "high": 174.5, "low": 168.5, "close": 170.0, "lots": 16932, "change_pct": 1.1904761904761905, "ma5": 169.9, "ma10": 171.2, "ma20": 166.35, "ma60": 146.25, "rsi6": 52.379512086416675, "rsi12": 57.84967173452554, "kd_k": 33.1701987617235, "kd_d": 40.90496789885535, "macd_osc": -1.051070576694185}, {"date": "2025-11-14", "taiex": 27397.5, "high": 166.0, "low": 160.0, "close": 160.5, "lots": 11552, "change_pct": -5.588235294117648, "ma5": 168.0, "ma10": 169.95, "ma20": 166.575, "ma60": 146.89166666666668, "rsi6": 29.164339978652265, "rsi12": 44.795618021147426, "kd_k": 22.926473971230298, "kd_d": 34.912136589647, "macd_osc": -1.7211584965160336}, {"date": "2025-11-17", "taiex": 27447.31, "high": 167.5, "low": 161.0, "close": 164.5, "lots": 11983, "change_pct": 2.4922118380062304, "ma5": 166.5, "ma10": 169.1, "ma20": 167.125, "ma60": 147.63333333333333, "rsi6": 42.124804369072464, "rsi12": 49.98017456251415, "kd_k": 23.855744552248765, "kd_d": 31.22667257718092, "macd_osc": -1.851802860528296}, {"date": "2025-11-18", "taiex": 26756.12, "high": 165.5, "low": 160.0, "close": 160.5, "lots": 12755, "change_pct": -2.43161094224924, "ma5": 164.7, "ma10": 167.75, "ma20": 167.35, "ma60": 148.36666666666667, "rsi6": 34.54103365441162, "rsi12": 45.33540547483059, "kd_k": 16.85621065388013, "kd_d": 26.436518602747324, "macd_osc": -2.143806538317291}, {"date": "2025-11-19", "taiex": 26580.12, "high": 159.5, "low": 153.0, "close": 154.0, "lots": 10946, "change_pct": -4.049844236760125, "ma5": 161.9, "ma10": 165.9, "ma20": 167.45, "ma60": 148.94166666666666, "rsi6": 25.56586834011823, "rsi12": 38.92308093101902, "kd_k": 12.598017986940494, "kd_d": 21.823685064145046, "macd_osc": -2.6762977834251487}, {"date": "2025-11-20", "taiex": 27426.36, "high": 161.5, "low": 157.0, "close": 158.5, "lots": 9120, "change_pct": 2.922077922077922, "ma5": 159.6, "ma10": 164.75, "ma20": 167.8, "ma60": 149.63333333333333, "rsi6": 38.781056732018115, "rsi12": 44.81781970998517, "kd_k": 15.88167185523924, "kd_d": 19.843013994509775, "macd_osc": -2.623513779739318}, {"date": "2025-11-21", "taiex": 26434.94, "high": 153.5, "low": 149.0, "close": 151.0, "lots": 7972, "change_pct": -4.73186119873817, "ma5": 157.7, "ma10": 162.85, "ma20": 167.85, "ma60": 150.175, "rsi6": 28.61892976271386, "rsi12": 38.12728754334789, "kd_k": 12.926962523375867, "kd_d": 17.537663504131803, "macd_osc": -2.9664900606957465}, {"date": "2025-11-24", "taiex": 26504.24, "high": 153.0, "low": 148.0, "close": 151.5, "lots": 6408, "change_pct": 0.33112582781456956, "ma5": 155.1, "ma10": 160.8, "ma20": 167.4, "ma60": 150.725, "rsi6": 30.084572044524492, "rsi12": 38.79182076964364, "kd_k": 13.02049073885435, "kd_d": 16.03193924903932, "macd_osc": -3.0222392960770317}, {"date": "2025-11-25", "taiex": 26912.17, "high": 155.0, "low": 151.0, "close": 152.0, "lots": 4108, "change_pct": 0.33003300330033003, "ma5": 153.4, "ma10": 159.05, "ma20": 166.175, "ma60": 151.26666666666668, "rsi6": 31.765806337557436, "rsi12": 39.50067451482047, "kd_k": 13.711773700116737, "kd_d": 15.258550732731791, "macd_osc": -2.8881494220725696}, {"date": "2025-11-26", "taiex": 27409.54, "high": 154.5, "low": 151.0, "close": 154.5, "lots": 4022, "change_pct": 1.644736842105263, "ma5": 153.5, "ma10": 157.7, "ma20": 164.8, "ma60": 151.86666666666667, "rsi6": 40.36932656435229, "rsi12": 43.09530180519681, "kd_k": 20.2522935778556, "kd_d": 16.923131681106394, "macd_osc": -2.507883280487349}, {"date": "2025-11-27", "taiex": 27554.53, "high": 156.5, "low": 154.5, "close": 155.5, "lots": 3772, "change_pct": 0.6472491909385114, "ma5": 152.9, "ma10": 156.25, "ma20": 163.725, "ma60": 152.475, "rsi6": 43.77235258986448, "rsi12": 44.53338350936453, "kd_k": 26.322041872416555, "kd_d": 20.056101744876447, "macd_osc": -2.0832633255488764}, {"date": "2025-11-28", "taiex": 27626.48, "high": 158.5, "low": 155.0, "close": 157.0, "lots": 3164, "change_pct": 0.964630225080386, "ma5": 154.1, "ma10": 155.9, "ma20": 162.925, "ma60": 153.10833333333332, "rsi6": 49.01018389753915, "rsi12": 46.736049424937775, "kd_k": 34.69088505780151, "kd_d": 24.9343628491848, "macd_osc": -1.6164455289372475}, {"date": "2025-12-01", "taiex": 27342.53, "high": 159.0, "low": 153.0, "close": 153.5, "lots": 6457, "change_pct": -2.229299363057325, "ma5": 154.5, "ma10": 154.8, "ma20": 161.95, "ma60": 153.675, "rsi6": 38.8713270125338, "rsi12": 42.44549059702795, "kd_k": 36.70750361878125, "kd_d": 28.85874310571695, "macd_osc": -1.4630544157057095}, {"date": "2025-12-02", "taiex": 27564.27, "high": 157.5, "low": 153.5, "close": 155.5, "lots": 4605, "change_pct": 1.3029315960912053, "ma5": 155.2, "ma10": 154.3, "ma20": 161.025, "ma60": 154.275, "rsi6": 46.46548657293587, "rsi12": 45.560955534773925, "kd_k": 42.99018759770602, "kd_d": 33.569224603046635, "macd_osc": -1.1598223431992296}, {"date": "2025-12-03", "taiex": 27793.04, "high": 161.5, "low": 156.5, "close": 158.5, "lots": 7053, "change_pct": 1.929260450160772, "ma5": 156.0, "ma10": 154.75, "ma20": 160.325, "ma60": 154.91666666666666, "rsi6": 56.24900724506302, "rsi12": 49.99065720780115, "kd_k": 54.586050991063274, "kd_d": 40.57483339905218, "macd_osc": -0.712107653083301}, {"date": "2025-12-04", "taiex": 27795.71, "high": 158.5, "low": 154.0, "close": 156.0, "lots": 6120, "change_pct": -1.5772870662460567, "ma5": 156.1, "ma10": 154.5, "ma20": 159.625, "ma60": 155.50833333333333, "rsi6": 47.55774995955402, "rsi12": 46.54742021079348, "kd_k": 56.14378708046193, "kd_d": 45.76448462618876, "macd_osc": -0.5466781148237658}, {"date": "2025-12-05", "taiex": 27980.89, "high": 157.5, "low": 155.0, "close": 157.0, "lots": 3762, "change_pct": 0.641025641025641, "ma5": 156.1, "ma10": 155.1, "ma20": 158.975, "ma60": 156.01666666666668, "rsi6": 51.17866731277216, "rsi12": 48.107096929018375, "kd_k": 56.47681043459366, "kd_d": 49.33525989565706, "macd_osc": -0.34224371736342163}, {"date": "2025-12-08", "taiex": 28303.78, "high": 161.5, "low": 157.5, "close": 160.0, "lots": 6247, "change_pct": 1.910828025477707, "ma5": 157.4, "ma10": 155.95, "ma20": 158.375, "ma60": 156.58333333333334, "rsi6": 60.89804157507331, "rsi12": 52.630587913860126, "kd_k": 66.22263552782434, "kd_d": 54.96438510637948, "macd_osc": 0.004336751563558283}, {"date": "2025-12-09", "taiex": 28182.6, "high": 164.0, "low": 160.0, "close": 160.5, "lots": 6476, "change_pct": 0.3125, "ma5": 158.4, "ma10": 156.8, "ma20": 157.925, "ma60": 157.14166666666668, "rsi6": 62.39531337495193, "rsi12": 53.36963462841487, "kd_k": 66.87569641248895, "kd_d": 58.934822208415966, "macd_osc": 0.26228925950240545}, {"date": "2025-12-10", "taiex": 28400.73, "high": 162.0, "low": 157.5, "close": 159.0, "lots": 5793, "change_pct": -0.9345794392523363, "ma5": 158.5, "ma10": 157.25, "ma20": 157.475, "ma60": 157.63333333333333, "rsi6": 54.8361827334808, "rsi12": 50.77694642427711, "kd_k": 62.765615790144146, "kd_d": 60.21175340232536, "macd_osc": 0.3229360438769129}, {"date": "2025-12-11", "taiex": 28024.75, "high": 164.5, "low": 158.5, "close": 162.0, "lots": 6452, "change_pct": 1.8867924528301887, "ma5": 159.7, "ma10": 157.9, "ma20": 157.075, "ma60": 157.96666666666667, "rsi6": 65.00983905808184, "rsi12": 55.49421972394812, "kd_k": 67.93070038183522, "kd_d": 62.784735728828636, "macd_osc": 0.5431796691296923}, {"date": "2025-12-12", "taiex": 28198.02, "high": 167.0, "low": 161.5, "close": 162.0, "lots": 7978, "change_pct": 0.0, "ma5": 160.7, "ma10": 158.4, "ma20": 157.15, "ma60": 158.15, "rsi6": 65.00983905808184, "rsi12": 55.49421972394812, "kd_k": 66.2747879088778, "kd_d": 63.948086455511685, "macd_osc": 0.6592189597763478}, {"date": "2025-12-15", "taiex": 27866.94, "high": 161.5, "low": 156.5, "close": 159.0, "lots": 10023, "change_pct": -1.8518518518518516, "ma5": 160.5, "ma10": 158.95, "ma20": 156.875, "ma60": 158.325, "rsi6": 49.08714123235061, "rsi12": 49.81299154553916, "kd_k": 57.00370475976469, "kd_d": 61.63329255692935, "macd_osc": 0.5109065360951899}, {"date": "2025-12-16", "taiex": 27536.66, "high": 161.5, "low": 152.0, "close": 155.5, "lots": 12512, "change_pct": -2.20125786163522, "ma5": 159.5, "ma10": 158.95, "ma20": 156.625, "ma60": 158.5, "rsi6": 36.55312807521048, "rsi12": 44.07076382659666, "kd_k": 45.7802476176209, "kd_d": 56.34894424382652, "macd_osc": 0.1716050702907851}, {"date": "2025-12-17", "taiex": 27525.17, "high": 165.0, "low": 156.0, "close": 162.0, "lots": 12984, "change_pct": 4.180064308681672, "ma5": 160.1, "ma10": 159.3, "ma20": 157.025, "ma60": 158.70833333333334, "rsi6": 59.56346231758475, "rsi12": 54.6597735089031, "kd_k": 52.74238730063615, "kd_d": 55.1467585960964, "macd_osc": 0.3681676319719862}, {"date": "2025-12-18", "taiex": 27468.53, "high": 165.0, "low": 160.0, "close": 161.5, "lots": 10915, "change_pct": -0.30864197530864196, "ma5": 160.0, "ma10": 159.85, "ma20": 157.175, "ma60": 158.89166666666668, "rsi6": 57.634029805255445, "rsi12": 53.804935583653126, "kd_k": 56.27270264486854, "kd_d": 55.52207327902045, "macd_osc": 0.44273247515269587}, {"date": "2025-12-19", "taiex": 27696.35, "high": 165.0, "low": 159.0, "close": 159.0, "lots": 9825, "change_pct": -1.5479876160990713, "ma5": 159.4, "ma10": 160.05, "ma20": 157.575, "ma60": 159.025, "rsi6": 48.25526557591921, "rsi12": 49.57586602378364, "kd_k": 53.07069065213457, "kd_d": 54.70494573672515, "macd_osc": 0.3082782950719779}, {"date": "2025-12-22", "taiex": 28149.64, "high": 174.5, "low": 164.0, "close": 172.0, "lots": 22521, "change_pct": 8.176100628930817, "ma5": 162.0, "ma10": 161.25, "ma20": 158.6, "ma60": 159.38333333333333, "rsi6": 74.32574660597867, "rsi12": 65.12556033361103, "kd_k": 65.010090064386, "kd_d": 58.139993845945426, "macd_osc": 1.0383345114582703}, {"date": "2025-12-23", "taiex": 28310.47, "high": 171.0, "low": 163.0, "close": 164.0, "lots": 15214, "change_pct": -4.651162790697675, "ma5": 163.7, "ma10": 161.6, "ma20": 159.2, "ma60": 159.6, "rsi6": 54.17099075689565, "rsi12": 53.95552544724634, "kd_k": 61.11783782070178, "kd_d": 59.132608504197535, "macd_osc": 0.9294408282208081}, {"date": "2025-12-24", "taiex": 28371.98, "high": 166.5, "low": 162.0, "close": 164.5, "lots": 9861, "change_pct": 0.3048780487804878, "ma5": 164.2, "ma10": 162.15, "ma20": 159.7, "ma60": 159.83333333333334, "rsi6": 55.084464578144996, "rsi12": 54.48775609962669, "kd_k": 59.2637437323197, "kd_d": 59.17632024690492, "macd_osc": 0.8407497466693279}, {"date": "2025-12-26", "taiex": 28556.02, "high": 180.0, "low": 166.5, "close": 175.0, "lots": 33706, "change_pct": 6.382978723404255, "ma5": 166.9, "ma10": 163.45, "ma20": 160.675, "ma60": 160.41666666666666, "rsi6": 70.10199195476926, "rsi12": 64.0164647163555, "kd_k": 66.89011486916552, "kd_d": 61.74758512099178, "macd_osc": 1.4056309969529337}, {"date": "2025-12-29", "taiex": 28810.89, "high": 177.5, "low": 169.5, "close": 176.5, "lots": 15895, "change_pct": 0.8571428571428572, "ma5": 170.4, "ma10": 164.9, "ma20": 161.65, "ma60": 160.925, "rsi6": 71.72276426910983, "rsi12": 65.15345320172763, "kd_k": 73.76007657944368, "kd_d": 65.75174894047575, "macd_osc": 1.772984022737794}, {"date": "2025-12-30", "taiex": 28707.13, "high": 177.5, "low": 173.0, "close": 175.0, "lots": 7416, "change_pct": -0.84985835694051, "ma5": 171.0, "ma10": 166.5, "ma20": 162.725, "ma60": 161.39166666666668, "rsi6": 67.34202720639044, "rsi12": 62.98245055742963, "kd_k": 75.56227327518467, "kd_d": 69.02192371871205, "macd_osc": 1.801778950852138}, {"date": "2025-12-31", "taiex": 28963.6, "high": 179.0, "low": 173.0, "close": 173.0, "lots": 10070, "change_pct": -1.1428571428571428, "ma5": 172.8, "ma10": 168.25, "ma20": 163.6, "ma60": 161.75833333333333, "rsi6": 61.346845051103294, "rsi12": 60.0709638506888, "kd_k": 72.59707107234533, "kd_d": 70.21363950325647, "macd_osc": 1.5808472939935192}, {"date": "2026-01-02", "taiex": 29349.81, "high": 185.0, "low": 173.5, "close": 183.5, "lots": 20224, "change_pct": 6.069364161849711, "ma5": 176.6, "ma10": 170.4, "ma20": 164.85, "ma60": 162.28333333333333, "rsi6": 75.23603522146212, "rsi12": 68.42941412125471, "kd_k": 79.80830379181995, "kd_d": 73.41186093277763, "macd_osc": 2.009091181171838}, {"date": "2026-01-05", "taiex": 30105.04, "high": 201.5, "low": 185.5, "close": 201.5, "lots": 32738, "change_pct": 9.809264305177113, "ma5": 181.9, "ma10": 174.4, "ma20": 167.125, "ma60": 163.00833333333333, "rsi6": 85.76121274826829, "rsi12": 77.3114929372511, "kd_k": 86.53886919454663, "kd_d": 77.78753035336729, "macd_osc": 3.2958298239601147}, {"date": "2026-01-06", "taiex": 30576.3, "high": 209.0, "low": 197.5, "close": 204.0, "lots": 38510, "change_pct": 1.240694789081886, "ma5": 187.4, "ma10": 178.9, "ma20": 169.475, "ma60": 163.775, "rsi6": 86.70311921131683, "rsi12": 78.23910174559902, "kd_k": 87.47981350558427, "kd_d": 81.01829140410628, "macd_osc": 4.056517729847322}, {"date": "2026-01-07", "taiex": 30435.47, "high": 214.0, "low": 203.0, "close": 205.5, "lots": 27622, "change_pct": 0.7352941176470588, "ma5": 193.5, "ma10": 182.25, "ma20": 171.75, "ma60": 164.55, "rsi6": 87.30763789231419, "rsi12": 78.80626267179827, "kd_k": 86.2044910550049, "kd_d": 82.74702462107248, "macd_osc": 4.374547419864331}, {"date": "2026-01-08", "taiex": 30360.55, "high": 207.0, "low": 199.0, "close": 203.0, "lots": 13994, "change_pct": -1.2165450121654502, "ma5": 199.5, "ma10": 186.15, "ma20": 173.875, "ma60": 165.375, "rsi6": 80.03073234915279, "rsi12": 75.24076624994893, "kd_k": 83.08369579105589, "kd_d": 82.85924834440029, "macd_osc": 4.133214740298298}, {"date": "2026-01-09", "taiex": 30288.96, "high": 203.0, "low": 190.5, "close": 200.0, "lots": 19559, "change_pct": -1.477832512315271, "ma5": 202.8, "ma10": 189.7, "ma20": 175.925, "ma60": 166.25, "rsi6": 71.4546756537786, "rsi12": 71.03357044591554, "kd_k": 78.23557247493613, "kd_d": 81.3180230545789, "macd_osc": 3.512606357608375}, {"date": "2026-01-12", "taiex": 30567.29, "high": 220.0, "low": 206.5, "close": 220.0, "lots": 26466, "change_pct": 10.0, "ma5": 206.5, "ma10": 194.2, "ma20": 178.825, "ma60": 167.41666666666666, "rsi6": 84.63054544766908, "rsi12": 79.4077273872098, "kd_k": 85.49038164995741, "kd_d": 82.7088092530384, "macd_osc": 4.146608956309159}, {"date": "2026-01-13", "taiex": 30707.22, "high": 242.0, "low": 230.0, "close": 242.0, "lots": 38182, "change_pct": 10.0, "ma5": 214.1, "ma10": 200.75, "ma20": 182.825, "ma60": 168.85, "rsi6": 90.44949489836188, "rsi12": 84.71156669971114, "kd_k": 90.3269210999716, "kd_d": 85.2481798686828, "macd_osc": 5.651926315479518}, {"date": "2026-01-14", "taiex": 30941.78, "high": 253.5, "low": 241.0, "close": 251.5, "lots": 47909, "change_pct": 3.925619834710744, "ma5": 223.3, "ma10": 208.4, "ma20": 187.45, "ma60": 170.48333333333332, "rsi6": 92.015870387186, "rsi12": 86.36582875684422, "kd_k": 92.71794739998106, "kd_d": 87.73810237911555, "macd_osc": 6.813852981892627}, {"date": "2026-01-15", "taiex": 30810.58, "high": 257.5, "low": 247.5, "close": 257.5, "lots": 18575, "change_pct": 2.3856858846918487, "ma5": 234.2, "ma10": 216.85, "ma20": 192.55, "ma60": 172.175, "rsi6": 92.8985904338931, "rsi12": 87.31175867556544, "kd_k": 95.14529826665404, "kd_d": 90.20716767496171, "macd_osc": 7.460746926214156}, {"date": "2026-01-16", "taiex": 31408.7, "high": 269.0, "low": 254.0, "close": 263.0, "lots": 19776, "change_pct": 2.1359223300970873, "ma5": 246.8, "ma10": 224.8, "ma20": 197.6, "ma60": 174.025, "rsi6": 93.66858692314689, "rsi12": 88.13494823724832, "kd_k": 94.21576147713242, "kd_d": 91.54336560901861, "macd_osc": 7.70200370536014}, {"date": "2026-01-19", "taiex": 31639.29, "high": 271.5, "low": 258.5, "close": 262.5, "lots": 22077, "change_pct": -0.19011406844106463, "ma5": 255.3, "ma10": 230.9, "ma20": 202.65, "ma60": 175.875, "rsi6": 92.57357267596198, "rsi12": 87.5714960494339, "kd_k": 92.44013728105124, "kd_d": 91.84228949969614, "macd_osc": 7.27590748154546}, {"date": "2026-01-20", "taiex": 31759.99, "high": 258.0, "low": 249.0, "close": 251.5, "lots": 19133, "change_pct": -4.190476190476191, "ma5": 257.2, "ma10": 235.65, "ma20": 207.275, "ma60": 177.56666666666666, "rsi6": 70.7411533399667, "rsi12": 75.92244977590144, "kd_k": 86.72963884580369, "kd_d": 90.13807261506531, "macd_osc": 5.767195257393471}, {"date": "2026-01-21", "taiex": 31246.37, "high": 255.0, "low": 238.0, "close": 239.5, "lots": 22835, "change_pct": -4.7713717693836974, "ma5": 254.8, "ma10": 239.05, "ma20": 210.65, "ma60": 178.88333333333333, "rsi6": 54.05311252256508, "rsi12": 65.54595609793253, "kd_k": 77.98436828403374, "kd_d": 86.08683783805478, "macd_osc": 3.5820472174132227}, {"date": "2026-01-22", "taiex": 31746.08, "high": 263.0, "low": 247.0, "close": 257.5, "lots": 27202, "change_pct": 7.515657620041753, "ma5": 254.8, "ma10": 244.5, "ma20": 215.325, "ma60": 180.23333333333332, "rsi6": 67.74808643991419, "rsi12": 71.84311722157886, "kd_k": 78.14342500986865, "kd_d": 83.43903356199273, "macd_osc": 2.9938370882007135}, {"date": "2026-01-23", "taiex": 31961.51, "high": 257.5, "low": 245.5, "close": 246.5, "lots": 16035, "change_pct": -4.271844660194175, "ma5": 251.5, "ma10": 249.15, "ma20": 219.425, "ma60": 181.30833333333334, "rsi6": 55.59601756873054, "rsi12": 64.0400554799576, "kd_k": 65.34862872143853, "kd_d": 77.40889861514133, "macd_osc": 1.579855839546216}, {"date": "2026-01-26", "taiex": 32064.52, "high": 259.5, "low": 248.0, "close": 257.5, "lots": 14568, "change_pct": 4.462474645030426, "ma5": 250.5, "ma10": 252.9, "ma20": 223.55, "ma60": 182.65, "rsi6": 63.46090069033743, "rsi12": 67.84945698329545, "kd_k": 62.96873755558589, "kd_d": 72.59551159528951, "macd_osc": 1.1228082775765174}, {"date": "2026-01-27", "taiex": 32317.92, "high": 280.0, "low": 258.0, "close": 263.5, "lots": 27034, "change_pct": 2.3300970873786406, "ma5": 252.9, "ma10": 255.05, "ma20": 227.9, "ma60": 184.15833333333333, "rsi6": 67.25693001347241, "rsi12": 69.75590701384311, "kd_k": 62.21725360848583, "kd_d": 69.13609226635495, "macd_osc": 0.9678599736946758}, {"date": "2026-01-28", "taiex": 32803.82, "high": 275.0, "low": 253.0, "close": 261.5, "lots": 42383, "change_pct": -0.7590132827324478, "ma5": 257.3, "ma10": 256.05, "ma20": 232.225, "ma60": 185.63333333333333, "rsi6": 64.57352511866355, "rsi12": 68.28352550020604, "kd_k": 60.12896272311753, "kd_d": 66.13371575194247, "macd_osc": 0.49763701907719593}, {"date": "2026-01-29", "taiex": 32536.27, "high": 269.0, "low": 251.0, "close": 255.5, "lots": 23718, "change_pct": -2.294455066921606, "ma5": 256.9, "ma10": 255.85, "ma20": 236.35, "ma60": 186.99166666666667, "rsi6": 56.46354466638232, "rsi12": 63.871326257401705, "kd_k": 53.97486403763391, "kd_d": 62.08076518050628, "macd_osc": -0.4019489851474596}, {"date": "2026-01-30", "taiex": 32063.75, "high": 261.0, "low": 250.0, "close": 254.0, "lots": 14962, "change_pct": -0.5870841487279843, "ma5": 258.4, "ma10": 254.95, "ma20": 239.875, "ma60": 188.35, "rsi6": 54.41336395886338, "rsi12": 62.765245138424746, "kd_k": 48.68165539016863, "kd_d": 57.61439525039373, "macd_osc": -1.235398035661973}, {"date": "2026-02-02", "taiex": 31624.03, "high": 251.5, "low": 238.0, "close": 244.5, "lots": 12320, "change_pct": -3.740157480314961, "ma5": 255.8, "ma10": 253.15, "ma20": 242.025, "ma60": 189.59166666666667, "rsi6": 42.645220367704674, "rsi12": 56.05806384038709, "kd_k": 37.61316708550924, "kd_d": 50.94731919543223, "macd_osc": -2.4914285369621894}, {"date": "2026-02-03", "taiex": 32195.36, "high": 262.0, "low": 252.5, "close": 257.0, "lots": 15716, "change_pct": 5.112474437627812, "ma5": 254.5, "ma10": 253.7, "ma20": 244.675, "ma60": 191.04166666666666, "rsi6": 57.24526681339636, "rsi12": 61.90191249429988, "kd_k": 40.15480980303791, "kd_d": 47.34981606463412, "macd_osc": -2.53681463689302}, {"date": "2026-02-04", "taiex": 32289.81, "high": 258.0, "low": 249.0, "close": 252.5, "lots": 8162, "change_pct": -1.7509727626459144, "ma5": 252.7, "ma10": 255.0, "ma20": 247.025, "ma60": 192.38333333333333, "rsi6": 51.57377523027402, "rsi12": 58.82932204470614, "kd_k": 38.27780970996178, "kd_d": 44.32581394641001, "macd_osc": -2.9001314369677225}, {"date": "2026-02-05", "taiex": 31801.27, "high": 249.0, "low": 241.0, "close": 244.0, "lots": 9558, "change_pct": -3.3663366336633667, "ma5": 250.4, "ma10": 253.65, "ma20": 249.075, "ma60": 193.625, "rsi6": 42.115937855324574, "rsi12": 53.37052375338424, "kd_k": 30.280444568545946, "kd_d": 39.64402415378865, "macd_osc": -3.692336042628483}, {"date": "2026-02-06", "taiex": 31782.92, "high": 244.5, "low": 232.0, "close": 239.5, "lots": 12296, "change_pct": -1.8442622950819672, "ma5": 247.5, "ma10": 252.95, "ma20": 251.05, "ma60": 194.81666666666666, "rsi6": 37.72128810702239, "rsi12": 50.655865926703925, "kd_k": 25.39529637903063, "kd_d": 34.89444822886931, "macd_osc": -4.448144305413667}, {"date": "2026-02-09", "taiex": 32404.62, "high": 253.5, "low": 243.0, "close": 243.0, "lots": 9794, "change_pct": 1.4613778705636742, "ma5": 247.2, "ma10": 251.5, "ma20": 252.2, "ma60": 196.03333333333333, "rsi6": 43.24833530621816, "rsi12": 52.6973373744198, "kd_k": 25.457329368966157, "kd_d": 31.748741942234922, "macd_osc": -4.620839796369221}, {"date": "2026-02-10", "taiex": 33072.97, "high": 247.0, "low": 238.5, "close": 240.0, "lots": 6978, "change_pct": -1.2345679012345678, "ma5": 243.8, "ma10": 249.15, "ma20": 252.1, "ma60": 197.35833333333332, "rsi6": 39.6307384088396, "rsi12": 50.73463655847553, "kd_k": 24.17876011985131, "kd_d": 29.22541466810705, "macd_osc": -4.823281501930987}, {"date": "2026-02-11", "taiex": 33605.71, "high": 244.0, "low": 236.5, "close": 243.0, "lots": 5723, "change_pct": 1.25, "ma5": 241.9, "ma10": 247.3, "ma20": 251.675, "ma60": 198.66666666666666, "rsi6": 45.13763070108611, "rsi12": 52.65816698705616, "kd_k": 28.34139563545643, "kd_d": 28.930741657223507, "macd_osc": -4.639856012705044}, {"date": "2026-02-23", "taiex": 33773.26, "high": 256.0, "low": 245.5, "close": 249.0, "lots": 13974, "change_pct": 2.4691358024691357, "ma5": 242.9, "ma10": 246.65, "ma20": 251.25, "ma60": 200.14166666666668, "rsi6": 54.99130831593514, "rsi12": 56.37451356781718, "kd_k": 37.783152645859836, "kd_d": 31.881545320102283, "macd_osc": -4.0221637466651075}, {"date": "2026-02-24", "taiex": 34700.82, "high": 263.0, "low": 250.5, "close": 257.5, "lots": 13295, "change_pct": 3.413654618473896, "ma5": 246.5, "ma10": 247.0, "ma20": 250.975, "ma60": 201.86666666666667, "rsi6": 65.51936039634943, "rsi12": 61.094476997233386, "kd_k": 52.6081232692829, "kd_d": 38.79040463649582, "macd_osc": -2.995950443014653}, {"date": "2026-02-25", "taiex": 35413.07, "high": 261.0, "low": 251.0, "close": 258.0, "lots": 12598, "change_pct": 0.1941747572815534, "ma5": 249.5, "ma10": 248.35, "ma20": 250.75, "ma60": 203.525, "rsi6": 66.07943646860306, "rsi12": 61.36272989664214, "kd_k": 63.02907142683375, "kd_d": 46.86996023327513, "macd_osc": -2.2711927979352975}, {"date": "2026-02-26", "taiex": 35414.49, "high": 261.0, "low": 249.0, "close": 258.0, "lots": 11824, "change_pct": 0.0, "ma5": 253.1, "ma10": 248.45, "ma20": 251.075, "ma60": 205.30833333333334, "rsi6": 66.07943646860306, "rsi12": 61.36272989664214, "kd_k": 69.97637019853433, "kd_d": 54.57209688836153, "macd_osc": -1.800107036949246}, {"date": "2026-03-02", "taiex": 35095.09, "high": 255.0, "low": 248.5, "close": 253.0, "lots": 8130, "change_pct": -1.937984496124031, "ma5": 255.1, "ma10": 248.5, "ma20": 251.75, "ma60": 207.0, "rsi6": 53.55322294289604, "rsi12": 56.70938516469666, "kd_k": 69.23155862697988, "kd_d": 59.45858413456764, "macd_osc": -1.827698503521928}, {"date": "2026-03-03", "taiex": 34323.65, "high": 255.5, "low": 228.0, "close": 231.0, "lots": 16095, "change_pct": -8.695652173913043, "ma5": 251.5, "ma10": 247.2, "ma20": 250.425, "ma60": 208.31666666666666, "rsi6": 26.764668740474548, "rsi12": 41.575785128557094, "kd_k": 49.01151527512943, "kd_d": 55.976227848088236, "macd_osc": -3.2471393953799854}, {"date": "2026-03-04", "taiex": 32828.88, "high": 225.0, "low": 211.0, "close": 217.0, "lots": 17470, "change_pct": -6.0606060606060606, "ma5": 243.4, "ma10": 244.95, "ma20": 248.95, "ma60": 209.35833333333332, "rsi6": 19.366781394070273, "rsi12": 35.07735988340727, "kd_k": 36.5204973629068, "kd_d": 49.490984353027756, "macd_osc": -4.946612907284461}, {"date": "2026-03-05", "taiex": 33672.94, "high": 230.0, "low": 219.5, "close": 224.5, "lots": 8740, "change_pct": 3.4562211981566824, "ma5": 236.7, "ma10": 243.1, "ma20": 247.3, "ma60": 210.50833333333333, "rsi6": 31.53266693995667, "rsi12": 40.511404182636305, "kd_k": 33.00084439578402, "kd_d": 43.994271033946504, "macd_osc": -5.349162127067382}, {"date": "2026-03-06", "taiex": 33599.54, "high": 228.0, "low": 220.0, "close": 225.0, "lots": 6359, "change_pct": 0.22271714922048996, "ma5": 230.1, "ma10": 241.6, "ma20": 245.375, "ma60": 211.64166666666668, "rsi6": 32.349235076396354, "rsi12": 40.8713377555092, "kd_k": 30.974921904881654, "kd_d": 39.654487990924885, "macd_osc": -5.352253855077102}, {"date": "2026-03-09", "taiex": 32110.42, "high": 209.5, "low": 202.5, "close": 202.5, "lots": 9323, "change_pct": -10.0, "ma5": 220.0, "ma10": 237.55, "ma20": 242.425, "ma60": 212.45833333333334, "rsi6": 19.676850159677073, "rsi12": 31.51165834630443, "kd_k": 20.64994793658777, "kd_d": 33.31964130614585, "macd_osc": -6.5604186911507725}, {"date": "2026-03-10", "taiex": 32771.87, "high": 218.0, "low": 208.5, "close": 214.5, "lots": 8259, "change_pct": 5.9259259259259265, "ma5": 216.7, "ma10": 234.1, "ma20": 240.375, "ma60": 213.44166666666666, "rsi6": 35.77803701110068, "rsi12": 39.564047916068084, "kd_k": 20.604238795332016, "kd_d": 29.081173802541237, "macd_osc": -6.243904085165742}, {"date": "2026-03-11", "taiex": 34114.19, "high": 220.0, "low": 215.5, "close": 215.5, "lots": 9337, "change_pct": 0.4662004662004662, "ma5": 216.4, "ma10": 229.9, "ma20": 238.45, "ma60": 214.39166666666668, "rsi6": 37.04010044962699, "rsi12": 40.20318423927348, "kd_k": 21.143566604295415, "kd_d": 26.435304736459294, "macd_osc": -5.676105343081226}, {"date": "2026-03-12", "taiex": 33581.86, "high": 212.5, "low": 201.0, "close": 204.5, "lots": 10237, "change_pct": -5.104408352668213, "ma5": 212.4, "ma10": 224.55, "ma20": 236.45, "ma60": 215.2, "rsi6": 29.410888427471633, "rsi12": 35.67574686599502, "kd_k": 16.236383852404895, "kd_d": 23.035664441774493, "macd_osc": -5.733446494552283}, {"date": "2026-03-13", "taiex": 33400.32, "high": 203.0, "low": 196.5, "close": 201.0, "lots": 11911, "change_pct": -1.7114914425427872, "ma5": 207.6, "ma10": 218.85, "ma20": 233.65, "ma60": 215.93333333333334, "rsi6": 27.26654543965813, "rsi12": 34.333673694375435, "kd_k": 13.366628782959195, "kd_d": 19.812652555502726, "macd_osc": -5.687907139469212}, {"date": "2026-03-16", "taiex": 33342.51, "high": 210.5, "low": 201.0, "close": 204.0, "lots": 8791, "change_pct": 1.4925373134328357, "ma5": 207.9, "ma10": 213.95, "ma20": 231.225, "ma60": 216.66666666666666, "rsi6": 32.34053016211239, "rsi12": 36.56505336048601, "kd_k": 16.37377242247031, "kd_d": 18.666359177825253, "macd_osc": -5.152492818517381}, {"date": "2026-03-17", "taiex": 33836.57, "high": 209.0, "low": 200.0, "close": 202.5, "lots": 11335, "change_pct": -0.7352941176470588, "ma5": 205.5, "ma10": 211.1, "ma20": 229.15, "ma60": 217.36666666666667, "rsi6": 31.04124257926415, "rsi12": 35.89965821232869, "kd_k": 16.885997535378216, "kd_d": 18.072905297009573, "macd_osc": -4.613537576652613}, {"date": "2026-03-18", "taiex": 34348.58, "high": 215.0, "low": 205.0, "close": 211.0, "lots": 18468, "change_pct": 4.197530864197531, "ma5": 204.6, "ma10": 210.5, "ma20": 227.725, "ma60": 218.23333333333332, "rsi6": 45.83787167078016, "rsi12": 42.381408336788695, "kd_k": 26.601247034167486, "kd_d": 20.91568587606221, "macd_osc": -3.4519240549820056}, {"date": "2026-03-19", "taiex": 33689.68, "high": 213.0, "low": 205.0, "close": 205.5, "lots": 9141, "change_pct": -2.6066350710900474, "ma5": 204.8, "ma10": 208.6, "ma20": 225.85, "ma60": 218.95833333333334, "rsi6": 39.29154754761456, "rsi12": 39.557848917028004, "kd_k": 30.5001221362535, "kd_d": 24.11049796279264, "macd_osc": -2.846513746979409}, {"date": "2026-03-20", "taiex": 33543.88, "high": 210.0, "low": 197.5, "close": 201.5, "lots": 10319, "change_pct": -1.9464720194647203, "ma5": 204.9, "ma10": 206.25, "ma20": 223.925, "ma60": 219.61666666666667, "rsi6": 34.93705188122799, "rsi12": 37.57188916563018, "kd_k": 27.425613339062615, "kd_d": 25.215536421549295, "macd_osc": -2.5192431702492266}, {"date": "2026-03-23", "taiex": 32722.5, "high": 196.0, "low": 190.0, "close": 192.0, "lots": 9255, "change_pct": -4.714640198511166, "ma5": 202.5, "ma10": 205.2, "ma20": 221.375, "ma60": 220.16666666666666, "rsi6": 26.550898361085984, "rsi12": 33.2472869919049, "kd_k": 20.505964448263963, "kd_d": 23.64567909712085, "macd_osc": -2.7287165392614163}, {"date": "2026-03-24", "taiex": 32612.24, "high": 199.0, "low": 188.0, "close": 192.0, "lots": 4633, "change_pct": 0.0, "ma5": 200.4, "ma10": 202.95, "ma20": 218.525, "ma60": 220.775, "rsi6": 26.55089836108597, "rsi12": 33.2472869919049, "kd_k": 18.60891457044758, "kd_d": 21.96675758822976, "macd_osc": -2.6511425716413575}, {"date": "2026-03-25", "taiex": 33439.11, "high": 210.0, "low": 199.0, "close": 203.5, "lots": 7192, "change_pct": 5.989583333333334, "ma5": 198.9, "ma10": 201.75, "ma20": 215.825, "ma60": 221.46666666666667, "rsi6": 48.21769331628925, "rsi12": 42.74179032242972, "kd_k": 31.541745516100853, "kd_d": 25.15842023085346, "macd_osc": -1.6577738259239023}, {"date": "2026-03-26", "taiex": 33337.62, "high": 211.5, "low": 198.5, "close": 198.5, "lots": 9624, "change_pct": -2.457002457002457, "ma5": 197.5, "ma10": 201.15, "ma20": 212.85, "ma60": 222.08333333333334, "rsi6": 41.78642264876455, "rsi12": 40.0405449590325, "kd_k": 33.990793307030195, "kd_d": 28.102544589579036, "macd_osc": -1.191689737411643}, {"date": "2026-03-27", "taiex": 33112.59, "high": 196.0, "low": 192.0, "close": 195.0, "lots": 6164, "change_pct": -1.7632241813602016, "ma5": 196.2, "ma10": 200.55, "ma20": 209.7, "ma60": 222.68333333333334, "rsi6": 37.576396674361106, "rsi12": 38.19710752183821, "kd_k": 31.302504179995438, "kd_d": 29.1691977863845, "macd_osc": -0.9820877572294364}, {"date": "2026-03-30", "taiex": 32518.16, "high": 198.0, "low": 188.0, "close": 196.0, "lots": 5917, "change_pct": 0.5128205128205128, "ma5": 197.0, "ma10": 199.75, "ma20": 206.85, "ma60": 223.08333333333334, "rsi6": 39.66070988341973, "rsi12": 39.071426588894326, "kd_k": 30.7448793298735, "kd_d": 29.694424967547498, "macd_osc": -0.6548136119821724}, {"date": "2026-03-31", "taiex": 31722.99, "high": 196.0, "low": 185.5, "close": 187.0, "lots": 7673, "change_pct": -4.591836734693878, "ma5": 196.0, "ma10": 198.2, "ma20": 204.65, "ma60": 223.46666666666667, "rsi6": 29.14920997603508, "rsi12": 34.306380373315946, "kd_k": 22.31476803809748, "kd_d": 27.234539324397492, "macd_osc": -0.9076252703493495}, {"date": "2026-04-01", "taiex": 33174.82, "high": 197.5, "low": 194.5, "close": 195.0, "lots": 6746, "change_pct": 4.27807486631016, "ma5": 194.3, "ma10": 196.6, "ma20": 203.55, "ma60": 223.975, "rsi6": 44.764532681870655, "rsi12": 41.253801935100114, "kd_k": 27.055999204885495, "kd_d": 27.175025951226825, "macd_osc": -0.4238017209243079}, {"date": "2026-04-02", "taiex": 32572.43, "high": 209.5, "low": 197.5, "close": 202.0, "lots": 13058, "change_pct": 3.5897435897435894, "ma5": 195.0, "ma10": 196.25, "ma20": 202.425, "ma60": 224.425, "rsi6": 55.144796607754046, "rsi12": 46.6403444498472, "kd_k": 39.19117895710315, "kd_d": 31.180410286518928, "macd_osc": 0.4335159418386141}, {"date": "2026-04-07", "taiex": 33229.82, "high": 206.0, "low": 191.0, "close": 192.0, "lots": 13094, "change_pct": -4.9504950495049505, "ma5": 194.4, "ma10": 195.3, "ma20": 200.775, "ma60": 224.68333333333334, "rsi6": 41.708065736726915, "rsi12": 40.80890477787136, "kd_k": 34.460785971402096, "kd_d": 32.27386884814665, "macd_osc": 0.3941021151030615}, {"date": "2026-04-08", "taiex": 34761.38, "high": 211.0, "low": 199.5, "close": 211.0, "lots": 10585, "change_pct": 9.895833333333332, "ma5": 197.4, "ma10": 197.2, "ma20": 201.2, "ma60": 225.28333333333333, "rsi6": 62.52650371941572, "rsi12": 52.99133912323818, "kd_k": 55.66616500657575, "kd_d": 40.071300900956345, "macd_osc": 1.6445145135247188}, {"date": "2026-04-09", "taiex": 34861.16, "high": 219.0, "low": 208.5, "close": 209.5, "lots": 13318, "change_pct": -0.7109004739336493, "ma5": 201.9, "ma10": 198.95, "ma20": 200.95, "ma60": 225.89166666666668, "rsi6": 60.480192234910305, "rsi12": 52.068389352284065, "kd_k": 60.99137368597587, "kd_d": 47.04465849596285, "macd_osc": 2.3258060281652266}, {"date": "2026-04-10", "taiex": 35417.83, "high": 217.5, "low": 212.0, "close": 214.5, "lots": 10746, "change_pct": 2.386634844868735, "ma5": 205.8, "ma10": 200.05, "ma20": 200.9, "ma60": 226.40833333333333, "rsi6": 65.0548116941613, "rsi12": 54.923300445802404, "kd_k": 69.51663718368539, "kd_d": 54.53531805853703, "macd_osc": 3.024183003991558}, {"date": "2026-04-13", "taiex": 35457.29, "high": 220.5, "low": 211.0, "close": 218.5, "lots": 11007, "change_pct": 1.8648018648018647, "ma5": 209.1, "ma10": 202.05, "ma20": 201.6, "ma60": 226.69166666666666, "rsi6": 68.5497208191044, "rsi12": 57.1506742404702, "kd_k": 77.77299621769501, "kd_d": 62.28121077825635, "macd_osc": 3.6259483521896234}, {"date": "2026-04-14", "taiex": 36296.12, "high": 237.5, "low": 217.0, "close": 217.5, "lots": 26374, "change_pct": -0.4576659038901602, "ma5": 214.2, "ma10": 204.3, "ma20": 202.425, "ma60": 226.91666666666666, "rsi6": 66.55291050980043, "rsi12": 56.39073767616132, "kd_k": 72.36148465795051, "kd_d": 65.64130207148773, "macd_osc": 3.8082612811090257}, {"date": "2026-04-15", "taiex": 36722.14, "high": 218.5, "low": 207.0, "close": 210.0, "lots": 15742, "change_pct": -3.4482758620689653, "ma5": 214.0, "ma10": 205.7, "ma20": 202.725, "ma60": 226.99166666666667, "rsi6": 52.729195430922516, "rsi12": 50.8577126950372, "kd_k": 61.86106145655482, "kd_d": 64.38122186651009, "macd_osc": 3.2946178021700456}, {"date": "2026-04-16", "taiex": 37132.02, "high": 217.0, "low": 208.5, "close": 212.5, "lots": 9445, "change_pct": 1.1904761904761905, "ma5": 214.6, "ma10": 208.25, "ma20": 203.225, "ma60": 227.15, "rsi6": 56.35536861753335, "rsi12": 52.55069348709321, "kd_k": 56.652894017631525, "kd_d": 61.80511258355057, "macd_osc": 3.002355907395936}, {"date": "2026-04-17", "taiex": 36804.34, "high": 212.5, "low": 206.0, "close": 207.5, "lots": 8355, "change_pct": -2.3529411764705883, "ma5": 213.2, "ma10": 209.5, "ma20": 203.05, "ma60": 227.275, "rsi6": 47.59319847479414, "rsi12": 48.876867474788405, "kd_k": 49.59655300100166, "kd_d": 57.73559272270093, "macd_osc": 2.378697097106748}, {"date": "2026-04-20", "taiex": 36958.8, "high": 212.0, "low": 206.0, "close": 208.0, "lots": 9838, "change_pct": 0.24096385542168677, "ma5": 211.1, "ma10": 210.1, "ma20": 203.175, "ma60": 227.075, "rsi6": 48.55307865488217, "rsi12": 49.26381007394421, "kd_k": 40.52050901821163, "kd_d": 51.99723148787116, "macd_osc": 1.9255939649324176}, {"date": "2026-04-21", "taiex": 37605.11, "high": 217.5, "low": 210.5, "close": 213.0, "lots": 13028, "change_pct": 2.403846153846154, "ma5": 210.2, "ma10": 212.2, "ma20": 203.75, "ma60": 226.59166666666667, "rsi6": 57.82317939951147, "rsi12": 53.133532948548556, "kd_k": 34.421080086215156, "kd_d": 46.138514353985826, "macd_osc": 1.8859349115197461}, {"date": "2026-04-22", "taiex": 37878.47, "high": 224.0, "low": 211.5, "close": 218.5, "lots": 17552, "change_pct": 2.5821596244131455, "ma5": 211.9, "ma10": 212.95, "ma20": 205.075, "ma60": 226.04166666666666, "rsi6": 65.92729469661523, "rsi12": 57.063342410590124, "kd_k": 36.17489995165666, "kd_d": 42.81730955320944, "macd_osc": 2.1351039948054726}, {"date": "2026-04-23", "taiex": 37714.15, "high": 225.5, "low": 203.0, "close": 207.0, "lots": 21061, "change_pct": -5.263157894736842, "ma5": 210.8, "ma10": 212.7, "ma20": 205.825, "ma60": 225.2, "rsi6": 44.48198478103725, "rsi12": 47.90151265468683, "kd_k": 27.981334267288016, "kd_d": 37.8719844579023, "macd_osc": 1.4624764847730687}, {"date": "2026-04-24", "taiex": 38932.4, "high": 213.0, "low": 207.5, "close": 210.0, "lots": 9866, "change_pct": 1.4492753623188406, "ma5": 211.3, "ma10": 212.25, "ma20": 206.15, "ma60": 224.31666666666666, "rsi6": 49.612859867094656, "rsi12": 50.17796442665702, "kd_k": 25.417507869013264, "kd_d": 33.720492261605955, "macd_osc": 1.1693678193754453}, {"date": "2026-04-27", "taiex": 39616.63, "high": 224.5, "low": 212.0, "close": 217.0, "lots": 17340, "change_pct": 3.3333333333333335, "ma5": 213.1, "ma10": 212.1, "ma20": 207.075, "ma60": 223.55833333333334, "rsi6": 59.971161053770054, "rsi12": 55.164725071143685, "kd_k": 37.68574598674958, "kd_d": 35.04224350332049, "macd_osc": 1.3821048833437717}, {"date": "2026-04-28", "taiex": 39521.73, "high": 222.0, "low": 213.0, "close": 218.5, "lots": 11208, "change_pct": 0.6912442396313364, "ma5": 214.2, "ma10": 212.2, "ma20": 208.25, "ma60": 223.00833333333333, "rsi6": 61.98092405828796, "rsi12": 56.18979644794243, "kd_k": 48.086793620796016, "kd_d": 39.39042687581233, "macd_osc": 1.5465969745964914}, {"date": "2026-04-29", "taiex": 39303.5, "high": 220.0, "low": 201.5, "close": 204.5, "lots": 30442, "change_pct": -6.407322654462242, "ma5": 211.4, "ma10": 211.65, "ma20": 208.675, "ma60": 222.425, "rsi6": 39.672152987208065, "rsi12": 45.57946738435298, "kd_k": 36.22452908053067, "kd_d": 38.335127610718445, "macd_osc": 0.6795283078544527}, {"date": "2026-04-30", "taiex": 38926.63, "high": 210.5, "low": 201.0, "close": 203.0, "lots": 26149, "change_pct": -0.7334963325183375, "ma5": 210.6, "ma10": 210.7, "ma20": 209.475, "ma60": 221.51666666666668, "rsi6": 37.91745935727173, "rsi12": 44.59520399048001, "kd_k": 26.87077448906126, "kd_d": 34.51367657016605, "macd_osc": 0.007522530180573195}, {"date": "2026-05-04", "taiex": 40705.14, "high": 223.0, "low": 208.0, "close": 223.0, "lots": 27700, "change_pct": 9.852216748768473, "ma5": 213.2, "ma10": 212.25, "ma20": 210.875, "ma60": 221.125, "rsi6": 63.64504815396024, "rsi12": 57.838252918990705, "kd_k": 47.84582244848982, "kd_d": 38.95772519627397, "macd_osc": 0.8650686723929029}, {"date": "2026-05-05", "taiex": 40769.29, "high": 237.0, "low": 220.0, "close": 227.5, "lots": 38739, "change_pct": 2.0179372197309418, "ma5": 215.3, "ma10": 214.2, "ma20": 212.15, "ma60": 220.625, "rsi6": 67.30347947953916, "rsi12": 60.174775258585996, "kd_k": 56.434252002696915, "kd_d": 44.78323413174828, "macd_osc": 1.6452088841788464}, {"date": "2026-05-06", "taiex": 41138.85, "high": 250.0, "low": 233.5, "close": 234.5, "lots": 48489, "change_pct": 3.076923076923077, "ma5": 218.5, "ma10": 216.35, "ma20": 214.275, "ma60": 220.14166666666668, "rsi6": 72.47406960999659, "rsi12": 63.59810993936221, "kd_k": 60.41195031472311, "kd_d": 49.99280619273989, "macd_osc": 2.491730715058762}, {"date": "2026-05-07", "taiex": 41933.78, "high": 236.0, "low": 226.0, "close": 230.5, "lots": 22861, "change_pct": -1.7057569296375266, "ma5": 223.7, "ma10": 217.55, "ma20": 215.25, "ma60": 219.625, "rsi6": 65.38395937251737, "rsi12": 60.363541473561604, "kd_k": 60.34266075403309, "kd_d": 53.442757713170955, "macd_osc": 2.627809725256177}]}